Workbook
Name a: [1]DicoRefFO!$A:$IV
Name AAA: [2]DicoRefFO!$1:$1048576
Name ATICA_DATA: #REF!
Name CAPE_DATA: #REF!
Name DicoRefFOTibco: #REF!
Name Field_Data_Types: #REF!
Name ListeMsg: '[3] ListeMessages'!$B$7:$E$180
Name ListeTypeEntite: [4]TypeEntite!$A$5:$A$18
Name Name: #REF!
Name TOTO: '[5]Data Elements Spreadsheet-GS'!#REF!
Name ZoneDicoRefFO: [3]DicoRefFO!$1:$1048576

Sheet Histo
A1: HISTORIQUE DES MODIFICATIONS
A2: Version | B2: Auteur | C2: Date | D2: Origine | E2: Description
A3: 25.13 | B3: A.Vounki | C3: 45777 | D3: Gestion | E3: remplacement de CodeSet par Codeset
A4: 25.13 | B4: A.MAVIOGHA | C4: 45777 | D4: CAPTURE | E4: Remplacement de l'attribut temp_stampingReference pour les objets fileData,remittanceData et transactionIdentification, par l'attribut stampingReference
A5: 25.13 | B5: A.MAVIOGHA | C5: 45777 | D5: TLP | E5: Modification du libellé de l'attribut ContryCode: Country à Acceptance System Contry Code
A7: 25.13 | B7: O.Addoum | C7: 45777 | D7: Emission | E7: Renommage attribut: cardContractDeferredCalendarCode --> cardAgreementDeferredCalendarCode cardContractCardAccountId --> cardAgreementAccountId cardContractEntityId --> cardAgreementEntityId cardContractEntityName --> cardAgreementEntityName cardContractId --> cardAgreementId internalRef --> internalReference Renommage codeset: cardContractCardDesignCode --> CardDesignCode CardContractDeferredCalendarCodeSet --> CardAgreementDeferredCalendarCodeSet Création de l'attribut : Environment.cardAgreement.requestId
A8: 25.13 | B8: A.Vounki | C8: 45777 | D8: Gestion | E8: Suppression du schemeMerchantId
A9: 25.13 | B9: A.MAVIOGHA | C9: 45777 | D9: CAPTURE | E9: Création de l'attribut stampingReference
A10: 25.13 | B10: A.MAVIOGHA | C10: 45777 | D10: TLP | E10: Création du Type temp_dialogTelerametrageFunctionCodeCodeset
A11: 25.13 | B11: A.MAVIOGHA | C11: 45777 | D11: TLP | E11: Correction du type de temp_versionCBCOM: Exact2NumericText en Exact2AlphaNumericText
A12: 25.13 | B12: A.MAVIOGHA | C12: 45777 | D12: TLP | E12: Création de l'attribut temp_dialogTelerametrageFunctionCode
A13: 25.13 | B13: B.Porcher | C13: 45776 | D13: Gestion | E13: merchantparameters.authorisedDuplicatedTransactions est de type Max4NumericText et pas Max999NumericText
A14: 25.13 | B14: B.Porcher | C14: 45776 | D14: Gestion | E14: Remplacement des 'é' par des 'e'
A15: 25.13 | B15: S.Lambert | C15: 45776 | D15: Contestation | E15: Revue des CodeSets : DisputeQualificationCodeset RefundDecisionCodeset RefundNatureCodeset StatusCodeCodeset
... A18: 25.13 | B18: A.MAVIOGHA | C18: 45776 | D18: CAPTURE | E18: L'attribut merchantProcessingId est obsolète
A19: 25.13 | B19: A.MAVIOGHA | C19: 29/04/205 | D19: CAPTURE | E19: L'attribut uniqueTransactionReference est obsolète
A20: 25.12 | B20: A.MAVIOGHA | C20: 45775 | D20: CAPTURE | E20: Création de l'attribut numberOfNonCompletedRemittanceTransactions
A21: 25.12 | B21: A.MAVIOGHA | C21: 45775 | D21: CAPTURE | E21: Création du Type ElectronicCommercelAuthentificationNatureCodeset
A22: 25.12 | B22: A.MAVIOGHA | C22: 45775 | D22: CAPTURE | E22: Création du Type TypeOfAdditionalDataCodeset
A23: 25.12 | B23: A.MAVIOGHA | C23: 45775 | D23: CAPTURE | E23: Création du Type AcceptanceSystemCurrentConnectingModeCodeset
A24: 25.12 | B24: A.MAVIOGHA | C24: 45775 | D24: CAPTURE | E24: Création du Type Exact10NumericText
A25: 25.12 | B25: A.MAVIOGHA | C25: 45775 | D25: CAPTURE | E25: Création de l'attribut debitwithTipNumber
A26: 25.12 | B26: A.MAVIOGHA | C26: 45775 | D26: CAPTURE | E26: Création de l'attribut debitwithTipAmount
A27: 25.12 | B27: A.MAVIOGHA | C27: 45775 | D27: CAPTURE | E27: Création de l'attribut totalTipAmount
A28: 25.12 | B28: A.MAVIOGHA | C28: 45775 | D28: CAPTURE | E28: Création de l'attribut debitwithDonationNumber
A29: 25.12 | B29: A.MAVIOGHA | C29: 45775 | D29: CAPTURE | E29: Création de l'attribut debitwithDonationAmount
A30: 25.12 | B30: A.MAVIOGHA | C30: 45775 | D30: CAPTURE | E30: Création de l'attribut totalDonationAmount
A31: 25.12 | B31: M.MARGHAD | C31: 45775 | D31: Référentiel commerçant | E31: Correction du type de authorisedDuplicatedTransactions : TrueFalseIndicator en Max999NumericText
... A82: 25.12 | B82: M.MARGHAD | C82: 45775 | D82: Référentiel commerçant | E82: Alimentation du CodeSet PaymentUseCaseCodeSet par : Quasi cash et Funds transfer,
A83: 25.12 | B83: A.MAVIOGHA | C83: 45771 | D83: TLP
A84: 25.12 | B84: A.MAVIOGHA | C84: 45771 | D84: TLP
A85: 25.12 | B85: A.MAVIOGHA | C85: 45771 | D85: TLP | E85: Création de l'attribut temp_alphabeticCodeOfCurrency1
A86: 25.12 | B86: A.MAVIOGHA | C86: 45771 | D86: TLP | E86: Création de l'attribut temp_conversionRate
A87: 25.12 | B87: A.MAVIOGHA | C87: 45771 | D87: TLP | E87: Création de l'attribut temp_languageAbbreviation
A88: 25.12 | B88: A.MAVIOGHA | C88: 45771 | D88: TLP | E88: Création de l'attribut temp_targetPercentageForRandomSelection
A89: 25.12 | B89: A.MAVIOGHA | C89: 45771 | D89: TLP | E89: Création de l'attribut temp_earlierGMTPeriod
A90: 25.12 | B90: A.MAVIOGHA | C90: 45771 | D90: TLP | E90: Création de l'attribut temp_laterGMTPeriod
A91: 25.12 | B91: A.MAVIOGHA | C91: 45771 | D91: TLP | E91: Création de l'attribut temp_gMTDifference
A92: 25.12 | B92: A.MAVIOGHA | C92: 45771 | D92: TLP | E92: Création de l'attribut temp_signOfTimeDifference
A93: 25.12 | B93: A.MAVIOGHA | C93: 45771 | D93: TLP | E93: Création de l'attribut temp_terminalApplicationVersionNumber
A94: 25.12 | B94: A.MAVIOGHA | C94: 45771 | D94: TLP | E94: Création de l'attribut temp_defaultEMVDolsForAnEMVCardApplication
A95: 25.12 | B95: A.MAVIOGHA | C95: 45771 | D95: TLP | E95: Création de l'attribut temp_listOfDataElements
A96: 25.12 | B96: A.MAVIOGHA | C96: 45771 | D96: TLP | E96: Création de l'attribut temp_numericCurrencyCode
... A291: 25.11 | B291: A.MAVIOGHA | C291: 45769 | D291: CAPTURE | E291: Création de l'attribut preAuthorisationDuration
A292: 25.11 | B292: O.Addoum | C292: 45769 | D292: Emission | E292: Création de l'attribut Environment.card.ownerId
A293: 25.11 | B293: O.Addoum | C293: 45769 | D293: Emission | E293: Création de l'attribut Environment.card.embossedZone
A294: 25.11 | B294: O.Addoum | C294: 45769 | D294: Emission | E294: Création de l'attribut Environment.card.embossedComplementaryData
A295: 25.11 | B295: O.Addoum | C295: 45769 | D295: Emission | E295: Création de l'attribut Environment.card.cardContractDeferredCalendarCode
A296: 25.11 | B296: O.Addoum | C296: 45769 | D296: Emission | E296: Création de l'attribut Environment.card.additionalInformationZone
A297: 25.11 | B297: O.Addoum | C297: 45769 | D297: Emission | E297: Création de l'attribut Environment.card.supplementZone1
A298: 25.11 | B298: O.Addoum | C298: 45769 | D298: Emission | E298: Création de l'attribut Environment.card.supplementZone2
A299: 25.11 | B299: O.Addoum | C299: 45769 | D299: Emission | E299: Création de l'attribut Environment.card.chainingSecretCodeId
A300: 25.11 | B300: O.Addoum | C300: 45769 | D300: Emission | E300: Création de l'attribut Environment.card.personalAccountNumberExternalInformation
A301: 25.11 | B301: O.Addoum | C301: 45769 | D301: Emission | E301: Création de l'attribut Environment.card.cardContractCardDesignCode
A302: 25.11 | B302: O.Addoum | C302: 45769 | D302: Emission | E302: Création de l'attribut Environment.card.cardholderPictureId
A303: 25.11 | B303: O.Addoum | C303: 45769 | D303: Emission | E303: Création de l'attribut Environment.card.subscribeShippingConditions
... A312: 25.11 | B312: O.Addoum | C312: 45769 | D312: Emission | E312: Changement de l'attribut Environment.card.contractCardAccountId Max36NumericText --> Max36AlphaNumericTex
A313: 25.11 | B313: B. Porcher | C313: 45768 | D313: Gestion interne | E313: DICO_COMPLET : La colonne B ne doit pas être utilisée pour produire les JSON Schéma, il faut utiliser la colonne B de l'onglet DICO_EXPORT
A314: 25.11 | B314: B. Porcher | C314: 45768 | D314: PRECOMP | E314: Creation provisoire des codeset suivants pour PRECOMP : temp_genericMerchandIdCheckCodeset / temp_treatmentContextCodeset / temp_authorizationCharacteristicsIndicatorCodeset / temp_merchantCommunicationMediaCodeset / temp_merchantMailCodeCodeset / temp_linkedTransactionNatureCodeset / temp_rejectionNatureCodeset
A315: 25.11 | B315: B. Porcher | C315: 45768 | D315: PRECOMP | E315: Création de Context/merchantParameters/temp_genericMerchandIdCheckCode/temp_genericMerchandIdCheckCodeset pour PRECOMP-PC21
A316: 25.11 | B316: B. Porcher | C316: 45768 | D316: PRECOMP | E316: Création de Context/transactionContext/temp_treatmentContext/treatmentContextCodeset pour PRECOMP-PC11
A317: 25.11 | B317: B. Porcher | C317: 45768 | D317: PRECOMP | E317: Création de Context/transactionContext /temp_authorizationCharacteristicsIndicator/authorizationCharacteristicsIndicatorCodeset pour PRECOMP-PC21
A318: 25.11 | B318: B. Porcher | C318: 45768 | D318: PRECOMP | E318: Création de Context/transactionContext /temp_responseCodeISO/Exact2Text pour PRECOMP-PC21
A319: 25.11 | B319: B. Porcher | C319: 45768 | D319: PRECOMP | E319: Création de Context/transactionContext /temp_securityTransactionMode /Exact2Text pour PRECOMP-PC21
A320: 25.11 | B320: B. Porcher | C320: 45768 | D320: PRECOMP | E320: Création de Context/transactionContext /temp_transactionConditions /Exact2Text pour PRECOMP-PC21
A321: 25.11 | B321: B. Porcher | C321: 45768 | D321: PRECOMP | E321: Création de environment/acquirer/temp_acquirerCountryCode/ISO3NumericCountryCode pour PRECOMP-PC21
A322: 25.11 | B322: B. Porcher | C322: 45768 | D322: PRECOMP | E322: Création de environment/acquirer/temp_acquirerCurrencyCode/ISO3NumericCurrencyCode pour PRECOMP-PC21
A323: 25.11 | B323: B. Porcher | C323: 45768 | D323: PRECOMP | E323: Création de environment/acquirer/temp_bankGroup/Exact5NumericText pour PRECOMP-PC03R
A324: 25.11 | B324: B. Porcher | C324: 45768 | D324: PRECOMP | E324: Création de environment/acquirer/temp_BOFax/PhoneNumberType pour PRECOMP-PC03R
... A556: 25.08 | B556: M.Marghad | C556: 45748 | D556: Référentiel commerçant | E556: Création de l'attribut merchantParameters.fraudReportingIndicator
A557: 25.08 | B557: A,MAVIOGHA | C557: 45717 | D557: CAPTURE | E557: Modification du SIRET du Max14NumericText en MAX14AlphanuméricText
A558: 25.08 | B558: A,MAVIOGHA | C558: 45747 | D558: CAPTURE | E558: Création du type structuré PostalAddressType
A559: 25.08 | B559: A,MAVIOGHA | C559: 45747 | D559: CAPTURE | E559: Modification du PanEntryModeCodeset en cardDataEntryModeCodeset
A560: 25.08 | B560: A.MAVIOGHA | C560: 45747 | D560: CAPTURE | E560: Création du type Max14AlphanumericText
A561: 25.08 | B561: A.MAVIOGHA | C561: 45747 | D561: CAPTURE | E561: Création du type CardholderAuthenticationCapabilitiesCodeset
A562: 25.08 | B562: A.MAVIOGHA | C562: 45747 | D562: CAPTURE | E562: Création du type CardhholderPickUpCapabilitiesCodeset
A563: 25.08 | B563: A.MAVIOGHA | C563: 45747 | D563: CAPTURE | E563: Création du type CardWriteCapabilitiesCodeset
A564: 25.08 | B564: A.MAVIOGHA | C564: 45747 | D564: CAPTURE | E564: Création du type MessageDisplayPrintCapabilitiesCodeset
A565: 25.08 | B565: A.MAVIOGHA | C565: 45747 | D565: CAPTURE | E565: Création du type PinReadingCapabilitiesCodeset
A566: 25.08 | B566: A.MAVIOGHA | C566: 45747 | D566: CAPTURE | E566: Création du type SystemAuthenticatingTheCardholderCodeset
A567: 25.08 | B567: A.MAVIOGHA | C567: 45747 | D567: CAPTURE | E567: Création du type StatusOfMessageDisplayPrintCapabilityCodeset
A568: 25.08 | B568: A.MAVIOGHA | C568: 45747 | D568: CAPTURE | E568: Création du type AcknowledgementRequestIndicatorCodeset
A569: 25.08 | B569: A.MAVIOGHA | C569: 45747 | D569: CAPTURE | E569: Création du type ImmediateActionCodset
A570: 25.08 | B570: A.MAVIOGHA | C570: 45747 | D570: CAPTURE | E570: Création du type NextActionCodeset
A571: 25.08 | B571: A.MAVIOGHA | C571: 45747 | D571: CAPTURE | E571: Création du type AdditionnalInformationForImmediateActionCodeset
... A635: 25.07 | B635: B. Porcher | C635: 45737 | D635: SMHSM | E635: Les 2 attirbuts suivants sont OBSOLETES Transaction.transactionDetails.bdkKeyEncryption Transaction.transactionDetails.ktKeyEncryption (Richard Benmoussa le 21/03/25)
A636: 25.06 | B636: A.Vounki | C636: 45734 | D636: gestion interne Iso20021 | E636: correction doublon de valeur dans le TransactionNatureCodeset
A637: 25.06 | B637: A.Vounki | C637: 45734 | D637: gestion interne Iso20022 | E637: Suppression du doublon Transaction.security.pinBlockFormat
A638: 25.06 | B638: A.Vounki | C638: 45734 | D638: gestion interne Iso20022 | E638: Suppression de l'onglet Header Technique : sous la responsabilité de Framework
A639: 25.06 | B639: A.Vounki | C639: 45734 | D639: gestion interne Iso20022 | E639: Le premier caractère de tous les types et codeset sont en majuscules
A640: 25.06 | B640: A.Vounki | C640: 45734 | D640: gestion interne Iso20022 | E640: Abandon de YesNoIndicator au profit de TrueFalseIndicator, les deux étant de même type : boolean
A641: 25.06 | B641: A.Vounki | C641: 45734 | D641: Histaa | E641: Création de l'attribut marketPlaceId
A642: 25.06 | B642: S.Lambert | C642: 45733 | D642: gestion interne Iso20022 | E642: Changement de type de ecommerceIndicator
A643: 25.06 | B643: S.Lambert | C643: 45733 | D643: Contestation | E643: Création des données et des types de manualIndicator schemeNature securizationNature vrolTransactionReference authorisationCode disputeTechnicalInternalId disputeAuditTrailTransactionEligibilityIndicator disputeDataId disputeInternalIdentification creationDateTime disputeCondition disputeQualification totalAmount transactionsNumber auditTrailFolderEligibilityIndicator et enrichissement de NetworkCodeset avec la valeur intra
A644: 25.06 | B644: A.Vounki | C644: 45733 | D644: Histaa | E644: Création des attributs storedDataCategory, storedData, foreignCurrencyIndicator
A645: 25.06 | B645: A.Vounki | C645: 45733 | D645: Histaa | E645: Rajout de AuthorisationEvent et ReversalEvent dans MessageFunctionCodeset
A646: 25.06 | B646: A.Vounki | C646: 45733 | D646: Histaa | E646: protocolVersion passe de Max8Text à Max50Text pour plus de flexibilité
A647: 25.06 | B647: B. Porcher | C647: 45733 | D647: Annonce Tréso | E647: Création du type UUIDType à usage universel
A648: 25.06 | B648: B. Porcher | C648: 45733 | D648: Annonce Tréso | E648: Création des attributs : TransactionContext.jurisdiction, TransactionContext.tracabilityEventID, TransactionContext.traceabilityService
A649: 25.06 | B649: B. Porcher | C649: 45733 | D649: Annonce Tréso | E649: Création des attributs : Acquirer.acquirerLeaderInstitutionId,
...

Sheet DICO_Export
C1: Champs calculés à partir de DICO_COMPLET
A2: Référence | B2: O/N | C2: Segment Message | D2: Object | E2: Attribute | F2: Type | G2: MinO | H2: MaxO | I2: Obsoletes | J2: Libellé | K2: CIFO | L2: CBAE | M2: CB2AF | N2: CB2A | O2: VISA | P2: MCD | Q2: Mainframe | R2: .
A3: 241112000000 | B3: O | C3: =VLOOKUP($A3,DICO_Complet!$A$3:$U$983,3,FALSE) -> ApiResponse | D3: =VLOOKUP($A3,DICO_Complet!$A$3:$U$983,4,FALSE) -> error | E3: =VLOOKUP($A3,DICO_Complet!$A$3:$U$983,5,FALSE) -> code | F3: =VLOOKUP($A3,DICO_Complet!$A$3:$U$983,6,FALSE) -> Max20Text | G3: =VLOOKUP($A3,DICO_Complet!$A$3:$U$983,7,FALSE) -> 0 | H3: =VLOOKUP($A3,DICO_Complet!$A$3:$U$983,8,FALSE) -> 0 | I3: =IF(VLOOKUP($A3,DICO_Complet!$A$3:$U$983,9,FALSE)<>0,VLOOKUP($A3,DICO_Complet!$A$3:$U$983,9,FALSE),"") | J3: =VLOOKUP($A3,DICO_Complet!$A$3:$U$983,10,FALSE) -> code | K3: =IF(VLOOKUP($A3,DICO_Complet!$A$3:$U$983,12,FALSE)=0,"",VLOOKUP($A3,DICO_Complet!$A$3:$U$983,12,FALSE)) | L3: =IF(VLOOKUP($A3,DICO_Complet!$A$3:$U$983,13,FALSE)=0,"",VLOOKUP($A3,DICO_Complet!$A$3:$U$983,13,FALSE)) | M3: =IF(VLOOKUP($A3,DICO_Complet!$A$3:$U$983,14,FALSE)=0,"",VLOOKUP($A3,DICO_Complet!$A$3:$U$983,14,FALSE)) | N3: =IF(VLOOKUP($A3,DICO_Complet!$A$3:$U$983,15,FALSE)=0,"",VLOOKUP($A3,DICO_Complet!$A$3:$U$983,15,FALSE)) | O3: =IF(VLOOKUP($A3,DICO_Complet!$A$3:$U$983,16,FALSE)=0,"",VLOOKUP($A3,DICO_Complet!$A$3:$U$983,16,FALSE)) | P3: =IF(VLOOKUP($A3,DICO_Complet!$A$3:$U$983,17,FALSE)=0,"",VLOOKUP($A3,DICO_Complet!$A$3:$U$983,17,FALSE)) | Q3: =IF(VLOOKUP($A3,DICO_Complet!$A$3:$U$983,18,FALSE)=0,"",VLOOKUP($A3,DICO_Complet!$A$3:$U$983,18,FALSE))
A4: 241112000001 | B4: O | C4: =VLOOKUP($A4,DICO_Complet!$A$3:$U$983,3,FALSE) -> ApiResponse | D4: =VLOOKUP($A4,DICO_Complet!$A$3:$U$983,4,FALSE) -> error | E4: =VLOOKUP($A4,DICO_Complet!$A$3:$U$983,5,FALSE) -> developerText | F4: =VLOOKUP($A4,DICO_Complet!$A$3:$U$983,6,FALSE) -> Max70Text | G4: =VLOOKUP($A4,DICO_Complet!$A$3:$U$983,7,FALSE) -> 0 | H4: =VLOOKUP($A4,DICO_Complet!$A$3:$U$983,8,FALSE) -> 0 | I4: =IF(VLOOKUP($A4,DICO_Complet!$A$3:$U$983,9,FALSE)<>0,VLOOKUP($A4,DICO_Complet!$A$3:$U$983,9,FALSE),"") | J4: =VLOOKUP($A4,DICO_Complet!$A$3:$U$983,10,FALSE) -> a text that explains the possible reason(s) of the error, and the possible corrections | K4: =IF(VLOOKUP($A4,DICO_Complet!$A$3:$U$983,12,FALSE)=0,"",VLOOKUP($A4,DICO_Complet!$A$3:$U$983,12,FALSE)) | L4: =IF(VLOOKUP($A4,DICO_Complet!$A$3:$U$983,13,FALSE)=0,"",VLOOKUP($A4,DICO_Complet!$A$3:$U$983,13,FALSE)) | M4: =IF(VLOOKUP($A4,DICO_Complet!$A$3:$U$983,14,FALSE)=0,"",VLOOKUP($A4,DICO_Complet!$A$3:$U$983,14,FALSE)) | N4: =IF(VLOOKUP($A4,DICO_Complet!$A$3:$U$983,15,FALSE)=0,"",VLOOKUP($A4,DICO_Complet!$A$3:$U$983,15,FALSE)) | O4: =IF(VLOOKUP($A4,DICO_Complet!$A$3:$U$983,16,FALSE)=0,"",VLOOKUP($A4,DICO_Complet!$A$3:$U$983,16,FALSE)) | P4: =IF(VLOOKUP($A4,DICO_Complet!$A$3:$U$983,17,FALSE)=0,"",VLOOKUP($A4,DICO_Complet!$A$3:$U$983,17,FALSE)) | Q4: =IF(VLOOKUP($A4,DICO_Complet!$A$3:$U$983,18,FALSE)=0,"",VLOOKUP($A4,DICO_Complet!$A$3:$U$983,18,FALSE))
A5: 241112000003 | B5: O | C5: =VLOOKUP($A5,DICO_Complet!$A$3:$U$983,3,FALSE) -> ApiResponse | D5: =VLOOKUP($A5,DICO_Complet!$A$3:$U$983,4,FALSE) -> error | E5: =VLOOKUP($A5,DICO_Complet!$A$3:$U$983,5,FALSE) -> moreInfo | F5: =VLOOKUP($A5,DICO_Complet!$A$3:$U$983,6,FALSE) -> Max256Text | G5: =VLOOKUP($A5,DICO_Complet!$A$3:$U$983,7,FALSE) -> 0 | H5: =VLOOKUP($A5,DICO_Complet!$A$3:$U$983,8,FALSE) -> 0 | I5: =IF(VLOOKUP($A5,DICO_Complet!$A$3:$U$983,9,FALSE)<>0,VLOOKUP($A5,DICO_Complet!$A$3:$U$983,9,FALSE),"") | J5: =VLOOKUP($A5,DICO_Complet!$A$3:$U$983,10,FALSE) -> URI to documents | K5: =IF(VLOOKUP($A5,DICO_Complet!$A$3:$U$983,12,FALSE)=0,"",VLOOKUP($A5,DICO_Complet!$A$3:$U$983,12,FALSE)) | L5: =IF(VLOOKUP($A5,DICO_Complet!$A$3:$U$983,13,FALSE)=0,"",VLOOKUP($A5,DICO_Complet!$A$3:$U$983,13,FALSE)) | M5: =IF(VLOOKUP($A5,DICO_Complet!$A$3:$U$983,14,FALSE)=0,"",VLOOKUP($A5,DICO_Complet!$A$3:$U$983,14,FALSE)) | N5: =IF(VLOOKUP($A5,DICO_Complet!$A$3:$U$983,15,FALSE)=0,"",VLOOKUP($A5,DICO_Complet!$A$3:$U$983,15,FALSE)) | O5: =IF(VLOOKUP($A5,DICO_Complet!$A$3:$U$983,16,FALSE)=0,"",VLOOKUP($A5,DICO_Complet!$A$3:$U$983,16,FALSE)) | P5: =IF(VLOOKUP($A5,DICO_Complet!$A$3:$U$983,17,FALSE)=0,"",VLOOKUP($A5,DICO_Complet!$A$3:$U$983,17,FALSE)) | Q5: =IF(VLOOKUP($A5,DICO_Complet!$A$3:$U$983,18,FALSE)=0,"",VLOOKUP($A5,DICO_Complet!$A$3:$U$983,18,FALSE))
A6: 241112000004 | B6: O | C6: =VLOOKUP($A6,DICO_Complet!$A$3:$U$983,3,FALSE) -> ApiResponse | D6: =VLOOKUP($A6,DICO_Complet!$A$3:$U$983,4,FALSE) -> error | E6: =VLOOKUP($A6,DICO_Complet!$A$3:$U$983,5,FALSE) -> text | F6: =VLOOKUP($A6,DICO_Complet!$A$3:$U$983,6,FALSE) -> Max40Text | G6: =VLOOKUP($A6,DICO_Complet!$A$3:$U$983,7,FALSE) -> 0 | H6: =VLOOKUP($A6,DICO_Complet!$A$3:$U$983,8,FALSE) -> 0 | I6: =IF(VLOOKUP($A6,DICO_Complet!$A$3:$U$983,9,FALSE)<>0,VLOOKUP($A6,DICO_Complet!$A$3:$U$983,9,FALSE),"") | J6: =VLOOKUP($A6,DICO_Complet!$A$3:$U$983,10,FALSE) -> short text that explains the error in a language that is useful for the end-user of the service | K6: =IF(VLOOKUP($A6,DICO_Complet!$A$3:$U$983,12,FALSE)=0,"",VLOOKUP($A6,DICO_Complet!$A$3:$U$983,12,FALSE)) | L6: =IF(VLOOKUP($A6,DICO_Complet!$A$3:$U$983,13,FALSE)=0,"",VLOOKUP($A6,DICO_Complet!$A$3:$U$983,13,FALSE)) | M6: =IF(VLOOKUP($A6,DICO_Complet!$A$3:$U$983,14,FALSE)=0,"",VLOOKUP($A6,DICO_Complet!$A$3:$U$983,14,FALSE)) | N6: =IF(VLOOKUP($A6,DICO_Complet!$A$3:$U$983,15,FALSE)=0,"",VLOOKUP($A6,DICO_Complet!$A$3:$U$983,15,FALSE)) | O6: =IF(VLOOKUP($A6,DICO_Complet!$A$3:$U$983,16,FALSE)=0,"",VLOOKUP($A6,DICO_Complet!$A$3:$U$983,16,FALSE)) | P6: =IF(VLOOKUP($A6,DICO_Complet!$A$3:$U$983,17,FALSE)=0,"",VLOOKUP($A6,DICO_Complet!$A$3:$U$983,17,FALSE)) | Q6: =IF(VLOOKUP($A6,DICO_Complet!$A$3:$U$983,18,FALSE)=0,"",VLOOKUP($A6,DICO_Complet!$A$3:$U$983,18,FALSE))
A7: 241112000002 | B7: O | C7: =VLOOKUP($A7,DICO_Complet!$A$3:$U$983,3,FALSE) -> ApiResponse | D7: =VLOOKUP($A7,DICO_Complet!$A$3:$U$983,4,FALSE) -> httpStatus | E7: =VLOOKUP($A7,DICO_Complet!$A$3:$U$983,5,FALSE) -> httpCode | F7: =VLOOKUP($A7,DICO_Complet!$A$3:$U$983,6,FALSE) -> Exact3NumericText | G7: =VLOOKUP($A7,DICO_Complet!$A$3:$U$983,7,FALSE) -> 0 | H7: =VLOOKUP($A7,DICO_Complet!$A$3:$U$983,8,FALSE) -> 0 | I7: =IF(VLOOKUP($A7,DICO_Complet!$A$3:$U$983,9,FALSE)<>0,VLOOKUP($A7,DICO_Complet!$A$3:$U$983,9,FALSE),"") | J7: =VLOOKUP($A7,DICO_Complet!$A$3:$U$983,10,FALSE) -> Status code http | K7: =IF(VLOOKUP($A7,DICO_Complet!$A$3:$U$983,12,FALSE)=0,"",VLOOKUP($A7,DICO_Complet!$A$3:$U$983,12,FALSE)) | L7: =IF(VLOOKUP($A7,DICO_Complet!$A$3:$U$983,13,FALSE)=0,"",VLOOKUP($A7,DICO_Complet!$A$3:$U$983,13,FALSE)) | M7: =IF(VLOOKUP($A7,DICO_Complet!$A$3:$U$983,14,FALSE)=0,"",VLOOKUP($A7,DICO_Complet!$A$3:$U$983,14,FALSE)) | N7: =IF(VLOOKUP($A7,DICO_Complet!$A$3:$U$983,15,FALSE)=0,"",VLOOKUP($A7,DICO_Complet!$A$3:$U$983,15,FALSE)) | O7: =IF(VLOOKUP($A7,DICO_Complet!$A$3:$U$983,16,FALSE)=0,"",VLOOKUP($A7,DICO_Complet!$A$3:$U$983,16,FALSE)) | P7: =IF(VLOOKUP($A7,DICO_Complet!$A$3:$U$983,17,FALSE)=0,"",VLOOKUP($A7,DICO_Complet!$A$3:$U$983,17,FALSE)) | Q7: =IF(VLOOKUP($A7,DICO_Complet!$A$3:$U$983,18,FALSE)=0,"",VLOOKUP($A7,DICO_Complet!$A$3:$U$983,18,FALSE))
A8: 250331114316 | B8: O | C8: =VLOOKUP($A8,DICO_Complet!$A$3:$U$983,3,FALSE) -> ApiResponse | D8: =VLOOKUP($A8,DICO_Complet!$A$3:$U$983,4,FALSE) -> httpStatus | E8: =VLOOKUP($A8,DICO_Complet!$A$3:$U$983,5,FALSE) -> requestId | F8: =VLOOKUP($A8,DICO_Complet!$A$3:$U$983,6,FALSE) -> Max36NumericText | G8: =VLOOKUP($A8,DICO_Complet!$A$3:$U$983,7,FALSE) -> 0 | H8: =VLOOKUP($A8,DICO_Complet!$A$3:$U$983,8,FALSE) -> 0 | I8: =IF(VLOOKUP($A8,DICO_Complet!$A$3:$U$983,9,FALSE)<>0,VLOOKUP($A8,DICO_Complet!$A$3:$U$983,9,FALSE),"") | J8: =VLOOKUP($A8,DICO_Complet!$A$3:$U$983,10,FALSE) -> Unique ID of API response | K8: =IF(VLOOKUP($A8,DICO_Complet!$A$3:$U$983,12,FALSE)=0,"",VLOOKUP($A8,DICO_Complet!$A$3:$U$983,12,FALSE)) | L8: =IF(VLOOKUP($A8,DICO_Complet!$A$3:$U$983,13,FALSE)=0,"",VLOOKUP($A8,DICO_Complet!$A$3:$U$983,13,FALSE)) | M8: =IF(VLOOKUP($A8,DICO_Complet!$A$3:$U$983,14,FALSE)=0,"",VLOOKUP($A8,DICO_Complet!$A$3:$U$983,14,FALSE)) | N8: =IF(VLOOKUP($A8,DICO_Complet!$A$3:$U$983,15,FALSE)=0,"",VLOOKUP($A8,DICO_Complet!$A$3:$U$983,15,FALSE)) | O8: =IF(VLOOKUP($A8,DICO_Complet!$A$3:$U$983,16,FALSE)=0,"",VLOOKUP($A8,DICO_Complet!$A$3:$U$983,16,FALSE)) | P8: =IF(VLOOKUP($A8,DICO_Complet!$A$3:$U$983,17,FALSE)=0,"",VLOOKUP($A8,DICO_Complet!$A$3:$U$983,17,FALSE)) | Q8: =IF(VLOOKUP($A8,DICO_Complet!$A$3:$U$983,18,FALSE)=0,"",VLOOKUP($A8,DICO_Complet!$A$3:$U$983,18,FALSE))
A9: 250331114321 | B9: O | C9: =VLOOKUP($A9,DICO_Complet!$A$3:$U$983,3,FALSE) -> Context | D9: =VLOOKUP($A9,DICO_Complet!$A$3:$U$983,4,FALSE) -> cardContext | E9: =VLOOKUP($A9,DICO_Complet!$A$3:$U$983,5,FALSE) -> acquiringChannel | F9: =VLOOKUP($A9,DICO_Complet!$A$3:$U$983,6,FALSE) -> AcquiringChannelCodeset | G9: =VLOOKUP($A9,DICO_Complet!$A$3:$U$983,7,FALSE) -> 0 | H9: =VLOOKUP($A9,DICO_Complet!$A$3:$U$983,8,FALSE) -> 0 | I9: =IF(VLOOKUP($A9,DICO_Complet!$A$3:$U$983,9,FALSE)<>0,VLOOKUP($A9,DICO_Complet!$A$3:$U$983,9,FALSE),"") | J9: =VLOOKUP($A9,DICO_Complet!$A$3:$U$983,10,FALSE) -> Indicates through which channel the action is triggered | K9: =IF(VLOOKUP($A9,DICO_Complet!$A$3:$U$983,12,FALSE)=0,"",VLOOKUP($A9,DICO_Complet!$A$3:$U$983,12,FALSE)) | L9: =IF(VLOOKUP($A9,DICO_Complet!$A$3:$U$983,13,FALSE)=0,"",VLOOKUP($A9,DICO_Complet!$A$3:$U$983,13,FALSE)) | M9: =IF(VLOOKUP($A9,DICO_Complet!$A$3:$U$983,14,FALSE)=0,"",VLOOKUP($A9,DICO_Complet!$A$3:$U$983,14,FALSE)) | N9: =IF(VLOOKUP($A9,DICO_Complet!$A$3:$U$983,15,FALSE)=0,"",VLOOKUP($A9,DICO_Complet!$A$3:$U$983,15,FALSE)) | O9: =IF(VLOOKUP($A9,DICO_Complet!$A$3:$U$983,16,FALSE)=0,"",VLOOKUP($A9,DICO_Complet!$A$3:$U$983,16,FALSE)) | P9: =IF(VLOOKUP($A9,DICO_Complet!$A$3:$U$983,17,FALSE)=0,"",VLOOKUP($A9,DICO_Complet!$A$3:$U$983,17,FALSE)) | Q9: =IF(VLOOKUP($A9,DICO_Complet!$A$3:$U$983,18,FALSE)=0,"",VLOOKUP($A9,DICO_Complet!$A$3:$U$983,18,FALSE))
A10: 241112000005 | B10: O | C10: =VLOOKUP($A10,DICO_Complet!$A$3:$U$983,3,FALSE) -> Context | D10: =VLOOKUP($A10,DICO_Complet!$A$3:$U$983,4,FALSE) -> cardContext | E10: =VLOOKUP($A10,DICO_Complet!$A$3:$U$983,5,FALSE) -> actionOnCard | F10: =VLOOKUP($A10,DICO_Complet!$A$3:$U$983,6,FALSE) -> ActivationCardCodeset | G10: =VLOOKUP($A10,DICO_Complet!$A$3:$U$983,7,FALSE) -> 0 | H10: =VLOOKUP($A10,DICO_Complet!$A$3:$U$983,8,FALSE) -> 0 | I10: =IF(VLOOKUP($A10,DICO_Complet!$A$3:$U$983,9,FALSE)<>0,VLOOKUP($A10,DICO_Complet!$A$3:$U$983,9,FALSE),"") | J10: =VLOOKUP($A10,DICO_Complet!$A$3:$U$983,10,FALSE) -> Action on card during transaction (activated, desactivated) | K10: =IF(VLOOKUP($A10,DICO_Complet!$A$3:$U$983,12,FALSE)=0,"",VLOOKUP($A10,DICO_Complet!$A$3:$U$983,12,FALSE)) -> AUT358/ AUT359 | L10: =IF(VLOOKUP($A10,DICO_Complet!$A$3:$U$983,13,FALSE)=0,"",VLOOKUP($A10,DICO_Complet!$A$3:$U$983,13,FALSE)) | M10: =IF(VLOOKUP($A10,DICO_Complet!$A$3:$U$983,14,FALSE)=0,"",VLOOKUP($A10,DICO_Complet!$A$3:$U$983,14,FALSE)) | N10: =IF(VLOOKUP($A10,DICO_Complet!$A$3:$U$983,15,FALSE)=0,"",VLOOKUP($A10,DICO_Complet!$A$3:$U$983,15,FALSE)) | O10: =IF(VLOOKUP($A10,DICO_Complet!$A$3:$U$983,16,FALSE)=0,"",VLOOKUP($A10,DICO_Complet!$A$3:$U$983,16,FALSE)) | P10: =IF(VLOOKUP($A10,DICO_Complet!$A$3:$U$983,17,FALSE)=0,"",VLOOKUP($A10,DICO_Complet!$A$3:$U$983,17,FALSE)) | Q10: =IF(VLOOKUP($A10,DICO_Complet!$A$3:$U$983,18,FALSE)=0,"",VLOOKUP($A10,DICO_Complet!$A$3:$U$983,18,FALSE))
A11: 250331162616 | B11: O | C11: =VLOOKUP($A11,DICO_Complet!$A$3:$U$983,3,FALSE) -> Context | D11: =VLOOKUP($A11,DICO_Complet!$A$3:$U$983,4,FALSE) -> cardContext | E11: =VLOOKUP($A11,DICO_Complet!$A$3:$U$983,5,FALSE) -> activationCodeForNoShowInvoice | F11: =VLOOKUP($A11,DICO_Complet!$A$3:$U$983,6,FALSE) -> Exact1AlphaNumericText | G11: =VLOOKUP($A11,DICO_Complet!$A$3:$U$983,7,FALSE) -> 0 | H11: =VLOOKUP($A11,DICO_Complet!$A$3:$U$983,8,FALSE) -> 0 | I11: =IF(VLOOKUP($A11,DICO_Complet!$A$3:$U$983,9,FALSE)<>0,VLOOKUP($A11,DICO_Complet!$A$3:$U$983,9,FALSE),"") | J11: =VLOOKUP($A11,DICO_Complet!$A$3:$U$983,10,FALSE) -> Activation code for no-show invoice | K11: =IF(VLOOKUP($A11,DICO_Complet!$A$3:$U$983,12,FALSE)=0,"",VLOOKUP($A11,DICO_Complet!$A$3:$U$983,12,FALSE)) | L11: =IF(VLOOKUP($A11,DICO_Complet!$A$3:$U$983,13,FALSE)=0,"",VLOOKUP($A11,DICO_Complet!$A$3:$U$983,13,FALSE)) | M11: =IF(VLOOKUP($A11,DICO_Complet!$A$3:$U$983,14,FALSE)=0,"",VLOOKUP($A11,DICO_Complet!$A$3:$U$983,14,FALSE)) -> 72_DF07 part 14 | N11: =IF(VLOOKUP($A11,DICO_Complet!$A$3:$U$983,15,FALSE)=0,"",VLOOKUP($A11,DICO_Complet!$A$3:$U$983,15,FALSE)) | O11: =IF(VLOOKUP($A11,DICO_Complet!$A$3:$U$983,16,FALSE)=0,"",VLOOKUP($A11,DICO_Complet!$A$3:$U$983,16,FALSE)) | P11: =IF(VLOOKUP($A11,DICO_Complet!$A$3:$U$983,17,FALSE)=0,"",VLOOKUP($A11,DICO_Complet!$A$3:$U$983,17,FALSE)) | Q11: =IF(VLOOKUP($A11,DICO_Complet!$A$3:$U$983,18,FALSE)=0,"",VLOOKUP($A11,DICO_Complet!$A$3:$U$983,18,FALSE))
A12: 250331162615 | B12: O | C12: =VLOOKUP($A12,DICO_Complet!$A$3:$U$983,3,FALSE) -> Context | D12: =VLOOKUP($A12,DICO_Complet!$A$3:$U$983,4,FALSE) -> cardContext | E12: =VLOOKUP($A12,DICO_Complet!$A$3:$U$983,5,FALSE) -> activCodePLBSInvoiceRemoteModeOrPreAuthProlongTransaction | F12: =VLOOKUP($A12,DICO_Complet!$A$3:$U$983,6,FALSE) -> Exact1AlphaNumericText | G12: =VLOOKUP($A12,DICO_Complet!$A$3:$U$983,7,FALSE) -> 0 | H12: =VLOOKUP($A12,DICO_Complet!$A$3:$U$983,8,FALSE) -> 0 | I12: =IF(VLOOKUP($A12,DICO_Complet!$A$3:$U$983,9,FALSE)<>0,VLOOKUP($A12,DICO_Complet!$A$3:$U$983,9,FALSE),"") | J12: =VLOOKUP($A12,DICO_Complet!$A$3:$U$983,10,FALSE) -> Activation code for invoice for the reservation and rental of goods or services in remote mode | K12: =IF(VLOOKUP($A12,DICO_Complet!$A$3:$U$983,12,FALSE)=0,"",VLOOKUP($A12,DICO_Complet!$A$3:$U$983,12,FALSE)) | L12: =IF(VLOOKUP($A12,DICO_Complet!$A$3:$U$983,13,FALSE)=0,"",VLOOKUP($A12,DICO_Complet!$A$3:$U$983,13,FALSE)) | M12: =IF(VLOOKUP($A12,DICO_Complet!$A$3:$U$983,14,FALSE)=0,"",VLOOKUP($A12,DICO_Complet!$A$3:$U$983,14,FALSE)) | N12: =IF(VLOOKUP($A12,DICO_Complet!$A$3:$U$983,15,FALSE)=0,"",VLOOKUP($A12,DICO_Complet!$A$3:$U$983,15,FALSE)) | O12: =IF(VLOOKUP($A12,DICO_Complet!$A$3:$U$983,16,FALSE)=0,"",VLOOKUP($A12,DICO_Complet!$A$3:$U$983,16,FALSE)) | P12: =IF(VLOOKUP($A12,DICO_Complet!$A$3:$U$983,17,FALSE)=0,"",VLOOKUP($A12,DICO_Complet!$A$3:$U$983,17,FALSE)) | Q12: =IF(VLOOKUP($A12,DICO_Complet!$A$3:$U$983,18,FALSE)=0,"",VLOOKUP($A12,DICO_Complet!$A$3:$U$983,18,FALSE))
A13: 250331162617 | B13: O | C13: =VLOOKUP($A13,DICO_Complet!$A$3:$U$983,3,FALSE) -> Context | D13: =VLOOKUP($A13,DICO_Complet!$A$3:$U$983,4,FALSE) -> cardContext | E13: =VLOOKUP($A13,DICO_Complet!$A$3:$U$983,5,FALSE) -> additionalInvoiceActivationCode | F13: =VLOOKUP($A13,DICO_Complet!$A$3:$U$983,6,FALSE) -> Exact1AlphaNumericText | G13: =VLOOKUP($A13,DICO_Complet!$A$3:$U$983,7,FALSE) -> 0 | H13: =VLOOKUP($A13,DICO_Complet!$A$3:$U$983,8,FALSE) -> 0 | I13: =IF(VLOOKUP($A13,DICO_Complet!$A$3:$U$983,9,FALSE)<>0,VLOOKUP($A13,DICO_Complet!$A$3:$U$983,9,FALSE),"") | J13: =VLOOKUP($A13,DICO_Complet!$A$3:$U$983,10,FALSE) -> Additional invoice activation code | K13: =IF(VLOOKUP($A13,DICO_Complet!$A$3:$U$983,12,FALSE)=0,"",VLOOKUP($A13,DICO_Complet!$A$3:$U$983,12,FALSE)) | L13: =IF(VLOOKUP($A13,DICO_Complet!$A$3:$U$983,13,FALSE)=0,"",VLOOKUP($A13,DICO_Complet!$A$3:$U$983,13,FALSE)) | M13: =IF(VLOOKUP($A13,DICO_Complet!$A$3:$U$983,14,FALSE)=0,"",VLOOKUP($A13,DICO_Complet!$A$3:$U$983,14,FALSE)) -> 72_DF07 part 13 | N13: =IF(VLOOKUP($A13,DICO_Complet!$A$3:$U$983,15,FALSE)=0,"",VLOOKUP($A13,DICO_Complet!$A$3:$U$983,15,FALSE)) | O13: =IF(VLOOKUP($A13,DICO_Complet!$A$3:$U$983,16,FALSE)=0,"",VLOOKUP($A13,DICO_Complet!$A$3:$U$983,16,FALSE)) | P13: =IF(VLOOKUP($A13,DICO_Complet!$A$3:$U$983,17,FALSE)=0,"",VLOOKUP($A13,DICO_Complet!$A$3:$U$983,17,FALSE)) | Q13: =IF(VLOOKUP($A13,DICO_Complet!$A$3:$U$983,18,FALSE)=0,"",VLOOKUP($A13,DICO_Complet!$A$3:$U$983,18,FALSE))
A14: 250410114322 | B14: O | C14: =VLOOKUP($A14,DICO_Complet!$A$3:$U$983,3,FALSE) -> Context | D14: =VLOOKUP($A14,DICO_Complet!$A$3:$U$983,4,FALSE) -> cardContext | E14: =VLOOKUP($A14,DICO_Complet!$A$3:$U$983,5,FALSE) -> blockingReasonCode | F14: =VLOOKUP($A14,DICO_Complet!$A$3:$U$983,6,FALSE) -> BlockingReasonCodeset | G14: =VLOOKUP($A14,DICO_Complet!$A$3:$U$983,7,FALSE) -> 0 | H14: =VLOOKUP($A14,DICO_Complet!$A$3:$U$983,8,FALSE) -> 0 | I14: =IF(VLOOKUP($A14,DICO_Complet!$A$3:$U$983,9,FALSE)<>0,VLOOKUP($A14,DICO_Complet!$A$3:$U$983,9,FALSE),"") | J14: =VLOOKUP($A14,DICO_Complet!$A$3:$U$983,10,FALSE) -> BlockingReasonCodeset | K14: =IF(VLOOKUP($A14,DICO_Complet!$A$3:$U$983,12,FALSE)=0,"",VLOOKUP($A14,DICO_Complet!$A$3:$U$983,12,FALSE)) | L14: =IF(VLOOKUP($A14,DICO_Complet!$A$3:$U$983,13,FALSE)=0,"",VLOOKUP($A14,DICO_Complet!$A$3:$U$983,13,FALSE)) | M14: =IF(VLOOKUP($A14,DICO_Complet!$A$3:$U$983,14,FALSE)=0,"",VLOOKUP($A14,DICO_Complet!$A$3:$U$983,14,FALSE)) | N14: =IF(VLOOKUP($A14,DICO_Complet!$A$3:$U$983,15,FALSE)=0,"",VLOOKUP($A14,DICO_Complet!$A$3:$U$983,15,FALSE)) | O14: =IF(VLOOKUP($A14,DICO_Complet!$A$3:$U$983,16,FALSE)=0,"",VLOOKUP($A14,DICO_Complet!$A$3:$U$983,16,FALSE)) | P14: =IF(VLOOKUP($A14,DICO_Complet!$A$3:$U$983,17,FALSE)=0,"",VLOOKUP($A14,DICO_Complet!$A$3:$U$983,17,FALSE)) | Q14: =IF(VLOOKUP($A14,DICO_Complet!$A$3:$U$983,18,FALSE)=0,"",VLOOKUP($A14,DICO_Complet!$A$3:$U$983,18,FALSE))
... A896: 241112000230 | B896: O | C896: =VLOOKUP($A896,DICO_Complet!$A$3:$U$983,3,FALSE) -> Transaction | D896: =VLOOKUP($A896,DICO_Complet!$A$3:$U$983,4,FALSE) -> transactionIdentification | E896: =VLOOKUP($A896,DICO_Complet!$A$3:$U$983,5,FALSE) -> transmissionGmtDateTime | F896: =VLOOKUP($A896,DICO_Complet!$A$3:$U$983,6,FALSE) -> ISODateTime | G896: =VLOOKUP($A896,DICO_Complet!$A$3:$U$983,7,FALSE) -> 0 | H896: =VLOOKUP($A896,DICO_Complet!$A$3:$U$983,8,FALSE) -> 0 | I896: =IF(VLOOKUP($A896,DICO_Complet!$A$3:$U$983,9,FALSE)<>0,VLOOKUP($A896,DICO_Complet!$A$3:$U$983,9,FALSE),"") | J896: =VLOOKUP($A896,DICO_Complet!$A$3:$U$983,10,FALSE) -> Transmission date and time GMT | K896: =IF(VLOOKUP($A896,DICO_Complet!$A$3:$U$983,12,FALSE)=0,"",VLOOKUP($A896,DICO_Complet!$A$3:$U$983,12,FALSE)) -> ISO7 | L896: =IF(VLOOKUP($A896,DICO_Complet!$A$3:$U$983,13,FALSE)=0,"",VLOOKUP($A896,DICO_Complet!$A$3:$U$983,13,FALSE)) -> [7] | M896: =IF(VLOOKUP($A896,DICO_Complet!$A$3:$U$983,14,FALSE)=0,"",VLOOKUP($A896,DICO_Complet!$A$3:$U$983,14,FALSE)) | N896: =IF(VLOOKUP($A896,DICO_Complet!$A$3:$U$983,15,FALSE)=0,"",VLOOKUP($A896,DICO_Complet!$A$3:$U$983,15,FALSE)) | O896: =IF(VLOOKUP($A896,DICO_Complet!$A$3:$U$983,16,FALSE)=0,"",VLOOKUP($A896,DICO_Complet!$A$3:$U$983,16,FALSE)) | P896: =IF(VLOOKUP($A896,DICO_Complet!$A$3:$U$983,17,FALSE)=0,"",VLOOKUP($A896,DICO_Complet!$A$3:$U$983,17,FALSE)) | Q896: =IF(VLOOKUP($A896,DICO_Complet!$A$3:$U$983,18,FALSE)=0,"",VLOOKUP($A896,DICO_Complet!$A$3:$U$983,18,FALSE))

Sheet DICO_Complet
A2: Référence | B2: N/A | C2: Segment Message | D2: Object | E2: Attribute | F2: Type | G2: N/A2 | H2: N/A3 | I2: Obsolète | J2: Libellé | K2: Commentaire | L2: CIFO | M2: CBAE | N2: CB2AF | O2: CB2A | P2: VISA | Q2: MCD | R2: Mainframe | S2: temp_ Data | T2: Demander PAR
A3: 241112000000 | B3: XXX | C3: ApiResponse | D3: error | E3: code | F3: Max20Text | J3: code
A4: 241112000001 | B4: XXX | C4: ApiResponse | D4: error | E4: developerText | F4: Max70Text | J4: a text that explains the possible reason(s) of the error, and the possible corrections
A5: 241112000003 | B5: XXX | C5: ApiResponse | D5: error | E5: moreInfo | F5: Max256Text | J5: URI to documents
A6: 241112000004 | B6: XXX | C6: ApiResponse | D6: error | E6: text | F6: Max40Text | J6: short text that explains the error in a language that is useful for the end-user of the service
A7: 241112000002 | B7: XXX | C7: ApiResponse | D7: httpStatus | E7: httpCode | F7: Exact3NumericText | J7: Status code http
A8: 250331114316 | B8: XXX | C8: ApiResponse | D8: httpStatus | E8: requestId | F8: Max36NumericText | J8: Unique ID of API response
A9: 250331114321 | B9: XXX | C9: Context | D9: cardContext | E9: acquiringChannel | F9: AcquiringChannelCodeset | J9: Indicates through which channel the action is triggered
A10: 241112000005 | B10: XXX | C10: Context | D10: cardContext | E10: actionOnCard | F10: ActivationCardCodeset | J10: Action on card during transaction (activated, desactivated) | K10: Activated, Desactivated or Nothing | L10: AUT358/ AUT359
A11: 250331162616 | B11: XXX | C11: Context | D11: cardContext | E11: activationCodeForNoShowInvoice | F11: Exact1AlphaNumericText | J11: Activation code for no-show invoice | N11: 72_DF07 part 14
A12: 250331162615 | B12: XXX | C12: Context | D12: cardContext | E12: activCodePLBSInvoiceRemoteModeOrPreAuthProlongTransaction | F12: Exact1AlphaNumericText | J12: Activation code for invoice for the reservation and rental of goods or services in remote mode
A13: 250331162617 | B13: XXX | C13: Context | D13: cardContext | E13: additionalInvoiceActivationCode | F13: Exact1AlphaNumericText | J13: Additional invoice activation code | N13: 72_DF07 part 13
A14: 250410114322 | B14: XXX | C14: Context | D14: cardContext | E14: blockingReasonCode | F14: BlockingReasonCodeset | J14: BlockingReasonCodeset
A15: 250410114323 | B15: XXX | C15: Context | D15: cardContext | E15: blockingRegulatoryReasonCode | F15: BlockingRegulatoryReasonCodeset | J15: BlockingRegulatoryReasonCodeset
A16: 250331114322 | B16: XXX | C16: Context | D16: cardContext | E16: contactlessActionCode | F16: TrueFalseIndicator | J16: Indicates if the contaclless feature is to be activated
A17: 250410114320 | B17: XXX | C17: Context | D17: cardContext | E17: contactlessActivationChoiceCode | F17: ContactlessActivationChoiceCodeset | J17: Choix activation du sans contact
A18: 250331162613 | B18: XXX | C18: Context | D18: cardContext | E18: forcingAuthorised | F18: Exact1AlphaNumericText | J18: Forcing Authorised
A19: 250331114323 | B19: XXX | C19: Context | D19: cardContext | E19: lockingActionCode | F19: TrueFalseIndicator | J19: indicates if the contract is blocked or not
A20: 250410114321 | B20: XXX | C20: Context | D20: cardContext | E20: lockingReasonCode | F20: LockingReasonCodeset | J20: LockingReasonCodeset
A21: 250331162610 | B21: XXX | C21: Context | D21: cardContext | E21: maximumLengthOfPAN | F21: Max2AlphaNumericText | J21: Maximum length of cardholder PAN | N21: 72_DF07 part 3
A22: 250331162609 | B22: XXX | C22: Context | D22: cardContext | E22: minimumLengthOfPAN | F22: Max2AlphaNumericText | J22: Minimum length of cardholder PAN | N22: 72_DF07 part 2
A23: 250410114325 | B23: XXX | C23: Context | D23: cardContext | E23: newSecretCodeIndicator | F23: TrueFalseIndicator | J23: TrueFalseIndicator
A24: 250331162611 | B24: XXX | C24: Context | D24: cardContext | E24: pinEntryTimer | F24: Exact2AlphaNumericText | J24: PIN entry timer | N24: 72_DF07 part 4
A25: 250331162612 | B25: XXX | C25: Context | D25: cardContext | E25: processingModeForNSCardApplicationCurrency | F25: Exact1AlphaNumericText | J25: Processing mode for non-supported card application currency | N25: 72_DF07 part 6
A26: 250410114324 | B26: XXX | C26: Context | D26: cardContext | E26: remanufacturingIndicator | F26: TrueFalseIndicator | J26: TrueFalseIndicator
A27: 250410114319 | B27: XXX | C27: Context | D27: cardContext | E27: secretCodeChoiceIndicator | F27: TrueFalseIndicator | J27: Indicateur du nouveaux code secret
A28: 250331114324 | B28: XXX | C28: Context | D28: cardContext | E28: secretCodeKnownIndicator | F28: TrueFalseIndicator | J28: Indicates if the secret code is known by the illegitimate holder of the card
A29: 250331114320 | B29: XXX | C29: Context | D29: cardContext | E29: semanticCheckIndicator | F29: TrueFalseIndicator | J29: Indicates if the action is a check or real action on card (Card activation)
A30: 250425201501 | C30: Context | D30: cardContext | E30: temp_applicationAIDLength | F30: Exact2NumericText | J30: Application AID length | N30: 72_DF8B part 2 | S30: OUI
A31: 250425201031 | C31: Context | D31: cardContext | E31: temp_cardProductLength | F31: Exact1HexBinaryText | J31: Card product length | N31: 72_DF49 part 3 | S31: OUI
A32: 250425201032 | C32: Context | D32: cardContext | E32: temp_cardProductValue | F32: Max5HexBinaryText | J32: Card product value | N32: 72_DF49 part 4 | S32: OUI
A33: 250425201508 | C33: Context | D33: cardContext | E33: temp_cVMSupported | F33: Exact1HexBinaryText | J33: CVM supported | N33: 72_DF89 part 1 | S33: OUI
A34: 250425201518 | C34: Context | D34: cardContext | E34: temp_cVMSupportedNoCvmRequired | F34: Exact1HexBinaryText | J34: CVM supported – No CVM Required | N34: 72_DFA9 part 5 | S34: OUI
A35: 250425200709 | C35: Context | D35: cardContext | E35: temp_defaultEMVDolsForAnEMVCardApplication | F35: DefaultEMVDolsForAnEMVCardApplicationCodeset | J35: DOL type | N35: 72_DF1A part 3 | S35: OUI
A36: 250425201506 | C36: Context | D36: cardContext | E36: temp_noOnDeviceCvm | F36: Exact12NumericText | J36: Reader Contactless Transaction limit (No On-Device CVM) | N36: 72_DF88 part 6 | S36: OUI
A37: 250425201507 | C37: Context | D37: cardContext | E37: temp_onDeviceCvm | F37: Exact12NumericText | J37: Reader Contactless Transaction limit (On-Device CVM) | N37: 72_DF88 part 7 | S37: OUI
A38: 250425201503 | C38: Context | D38: cardContext | E38: temp_readerContactlessFloorLimit | F38: Exact12NumericText | J38: Reader Contactless Floor limit | N38: 72_DF88 part 3 | S38: OUI
A39: 250425201505 | C39: Context | D39: cardContext | E39: temp_readerContactlessTransactionLimit | F39: Exact12NumericText | J39: Reader Contactless Transaction limit | N39: 72_DF88 part 5 | S39: OUI
A40: 250425201504 | C40: Context | D40: cardContext | E40: temp_readerCvmRequiredLimit | F40: Exact12NumericText | J40: Reader CVM Required Limit | N40: 72_DF88 part 4 | S40: OUI
A41: 250425201509 | C41: Context | D41: cardContext | E41: temp_statusCheckSupportFlag | F41: TrueFalseIndicator | J41: Status check support flag | N41: 72_DF89 part 2 | S41: OUI
... A45: 250425201519 | C45: Context | D45: cardContext | E45: temp_zeroAmountForOfflineAllowedFlag | F45: TrueFalseIndicator | J45: Zero amount for offline allowed flag | N45: 72_DFA9 part 6 | S45: OUI
A46: 250331162614 | B46: XXX | C46: Context | D46: cardContext | E46: typeOfAuthorisationRequestTrigger | F46: Exact1AlphaNumericText | J46: Type of authorisation request trigger
A47: 250410114318 | B47: XXX | C47: Context | D47: cardContext | E47: urgentManufacturingIndicator | F47: TrueFalseIndicator | J47: Indicateur personnalisation urgente
A48: 250415114200 | B48: XXX | C48: Context | D48: merchantParameters | E48: acquiringAllowedServices | F48: AcquiringAllowedServicesCodeset | J48: authorised front services
A49: 250428083000 | C49: Context | D49: merchantParameters | E49: additionalInvoiceIndicator | F49: TrueFalseIndicator | J49: Indicate if the merchant can do additional invoices
A50: 250415120100 | B50: XXX | C50: Context | D50: merchantParameters | E50: addressUse | F50: AddressUseCodeset | J50: Address use cases
A51: 250428083400 | C51: Context | D51: merchantParameters | E51: authorisationFloorLimit | F51: AmountType | J51: Indicate the floor limite an online authorisation has to be done.(Use AmountType structure and Amount attribute)
A52: 250428082600 | C52: Context | D52: merchantParameters | E52: authorisationForcingIndicator | F52: TrueFalseIndicator | J52: Indicate if the authorisation can be forced or not
A53: 250401135800 | B53: XXX | C53: Context | D53: merchantParameters | E53: authorisedDuplicatedTransactions | F53: Max4NumericText | J53: Number of authorised duplicated transactions
A54: 250408115500 | B54: XXX | C54: Context | D54: merchantParameters | E54: bigAmountControlIndicator | F54: TrueFalseIndicator | J54: Incation whether the merchant transactions needs to be checked when it is higher than an amount
A55: 250415114400 | B55: XXX | C55: Context | D55: merchantParameters | E55: blacklistDistributionIndicator | F55: TrueFalseIndicator | J55: Blacklist distribution indicator
A56: 250415114500 | B56: XXX | C56: Context | D56: merchantParameters | E56: blacklistDistributionRegions | F56: BlacklistDistributionRegionsCodeset | J56: Blacklist distribution regions
A57: 250408114800 | B57: XXX | C57: Context | D57: merchantParameters | E57: businessGroupingIdentifier | F57: Max35Text | J57: Business grouping identifier
A58: 250415114600 | B58: XXX | C58: Context | D58: merchantParameters | E58: cardBlockingListDistributionIndicator | F58: TrueFalseIndicator | J58: Card blocking distribution Indicator
A59: 250408115000 | B59: XXX | C59: Context | D59: merchantParameters | E59: chainingCode | F59: Max10Text | J59: Chaining code
A60: 250428083250 | C60: Context | D60: merchantParameters | E60: contactlessCreditIndicator | F60: TrueFalseIndicator | J60: Indicate if the merchant can do contactless credit (open payment)
A61: 250408114500 | B61: XXX | C61: Context | D61: merchantParameters | E61: contractCategory | F61: ContractCategoryCodeset | J61: Merchant contract Type : CB / DC (Dynamic Currency Conversion) / CP (China Union Pay) / DF DFS) / JC (Japan Credit Bureau)
A62: 250408115100 | B62: XXX | C62: Context | D62: merchantParameters | E62: contractProductCode | F62: Max6Text | J62: Code du produit carte
A63: 250401140100 | B63: XXX | C63: Context | D63: merchantParameters | E63: creditGroupingIndicator | F63: TrueFalseIndicator | J63: Credit groupig indicator
A64: 250415115300 | B64: XXX | C64: Context | D64: merchantParameters | E64: creditIndicator | F64: TrueFalseIndicator | J64: Indicate if credit is authorised
A65: 250428082700 | C65: Context | D65: merchantParameters | E65: defferedClearingIndicator | F65: TrueFalseIndicator | J65: Indicate if the merchant can deffer the clearing of transactions (open payment)
A66: 250401135700 | B66: XXX | C66: Context | D66: merchantParameters | E66: duplicatedTransactionControlIndicator | F66: TrueFalseIndicator | J66: Indicator for duplicated transactions check
A67: 250415114900 | B67: XXX | C67: Context | D67: merchantParameters | E67: dynamicLineIndicator | F67: TrueFalseIndicator | J67: Indicator Ligne Plaque Dynamique
A68: 250415120000 | B68: XXX | C68: Context | D68: merchantParameters | E68: feesCumulLevel | F68: FeesCumulLevelCodeset | J68: Fees Cumul Level
A69: 250415115900 | B69: XXX | C69: Context | D69: merchantParameters | E69: feesDebitPeriod | F69: Max10AlphaNumericText | J69: Period frequency of fees debit
A70: 250408115300 | B70: XXX | C70: Context | D70: merchantParameters | E70: feesDeferredDebitIndicator | F70: TrueFalseIndicator | J70: Indication whether the merchant has opted for a debit corresponding to the daily remittance, without soustracting the fees
A71: 250415115400 | B71: XXX | C71: Context | D71: merchantParameters | E71: forbiddenCardProduct | F71: ForbiddenCardProductCodeset | J71: Non-authorised card products
A72: 250401140800 | B72: XXX | C72: Context | D72: merchantParameters | E72: fraudReportingIndicator | F72: TrueFalseIndicator | J72: Fraud reporting indicator
A73: 250415115200 | B73: XXX | C73: Context | D73: merchantParameters | E73: genericMidControl | F73: GenericMidControlCodeset | J73: How control is done on MID
A74: 250401140700 | B74: XXX | C74: Context | D74: merchantParameters | E74: governmentControlCountryCode | F74: ISO3NumericCountryCode | J74: government country code
A75: 250401140600 | B75: XXX | C75: Context | D75: merchantParameters | E75: governmentControlIndicator | F75: TrueFalseIndicator | J75: Government control indicator
A76: 250408115200 | B76: XXX | C76: Context | D76: merchantParameters | E76: grossAmountIndicator | F76: TrueFalseIndicator | J76: Indication whether the merchant has subscribed to the monthly billing of the acquring fees
A77: 250415114800 | B77: XXX | C77: Context | D77: merchantParameters | E77: ibanUse | F77: IbanUseCodeset | J77: How iban is used
A78: 250428083100 | C78: Context | D78: merchantParameters | E78: informationRequestIndicator | F78: TrueFalseIndicator | J78: Indicate if the merchant can do information requests
A79: 250408114600 | B79: XXX | C79: Context | D79: merchantParameters | E79: mainGroupingIdentifier | F79: Max35Text | J79: Identifiant de regroupement principal Main grouping identifier
A80: 250428083500 | C80: Context | D80: merchantParameters | E80: maximumAuthorisedAmount | F80: AmountType | J80: Indicate the maximum amount the merchant is authorised to sell
A81: 250401140000 | B81: XXX | C81: Context | D81: merchantParameters | E81: maximumAuthorisedCredit | F81: AmountType | J81: Credit maximum authorised amount and currency
A82: 250401135900 | B82: XXX | C82: Context | D82: merchantParameters | E82: maximumAuthorisedDebit | F82: AmountType | J82: Debit maximum authorised amount and currency
A83: 250415120200 | B83: XXX | C83: Context | D83: merchantParameters | E83: merchantCreditCalculationDate | F83: MerchantCreditCalculationDateCodeset | J83: Merchant credit calculation date
A84: 250415115100 | B84: XXX | C84: Context | D84: merchantParameters | E84: merchantFeesAccounting | F84: MerchantFeesAccountingCodeset | J84: Merchant fees accounting frequency
A85: 250415115700 | B85: XXX | C85: Context | D85: merchantParameters | E85: merchantSchemeChoice | F85: BrandCodeset | J85: Switch preferences
A86: 250401135500 | B86: XXX | C86: Context | D86: merchantParameters | E86: noShowIndicator | F86: TrueFalseIndicator | J86: No show Indicator
A87: 250428082800 | C87: Context | D87: merchantParameters | E87: panTruncationIndicator | F87: TrueFalseIndicator | J87: Indicate if the merchant can use truncated PAN
A88: 250428082900 | C88: Context | D88: merchantParameters | E88: partialAuthorisationIndicator | F88: TrueFalseIndicator | J88: Indicate if the merchant can do partial authorisations
A89: 250401135000 | B89: XXX | C89: Context | D89: merchantParameters | E89: paymentFacilitatorIndicator | F89: TrueFalseIndicator | J89: Payment facilitator indicator
A90: 250415131001 | B90: XXX | C90: Context | D90: merchantParameters | E90: paymentGatewayId | F90: Exact11Text | J90: Gateway payment identifier | O90: 119-0204
A91: 250401135200 | B91: XXX | C91: Context | D91: merchantParameters | E91: paymentProtocolCategory | F91: PaymentProtocolCategoryCodeset | J91: Payment protocol category
A92: 250401135400 | B92: XXX | C92: Context | D92: merchantParameters | E92: paymentProtocolVersion | F92: PaymentProtocolVersionCodeset | J92: Payment protocol version
A93: 250415115500 | B93: XXX | C93: Context | D93: merchantParameters | E93: paymentRiskProfile | F93: Exact3Text | J93: Payment risk profile
A94: 250415120300 | B94: XXX | C94: Context | D94: merchantParameters | E94: postingCalendar | F94: PostingCalendarCodeset | J94: Posting based on calendar
A95: 250415115800 | B95: XXX | C95: Context | D95: merchantParameters | E95: recurringFeesDebitIndicator | F95: TrueFalseIndicator | J95: Indicator if fees debit recurrence is authorised
A96: 250415120400 | B96: XXX | C96: Context | D96: merchantParameters | E96: remittanceReceptionCutOff | F96: Max6NumericText | J96: Remittance reception Limit hour
A97: 250408114700 | B97: XXX | C97: Context | D97: merchantParameters | E97: secundaryGroupingIdentifier | F97: Max35Text | J97: Identifiant de regroupement secondaire Secondary grouping identifier
A98: 250428083300 | C98: Context | D98: merchantParameters | E98: singleTapIndicator | F98: TrueFalseIndicator | J98: Indicate if the merchant can use single tap service
A99: 250408115400 | B99: XXX | C99: Context | D99: merchantParameters | E99: statementIndicator | F99: TrueFalseIndicator | J99: Indication whether the merchant get the option to periodic numeric statement reports
A100: 250415114700 | B100: XXX | C100: Context | D100: merchantParameters | E100: telecomIndicator | F100: Exact2Text | J100: Telecom Indicator
A101: 250425200700 | C101: Context | D101: merchantParameters | E101: temp_alphabeticCodeOfCurrency1 | F101: ISO3AlphabeticCurrencyCode | J101: Alphabetic code of currency 1 | N101: 72_DF01 part 2 | S101: OUI
A102: 250418220100 | B102: XXX | C102: Context | D102: merchantParameters | E102: temp_commissionProcessingLevelCode | F102: temp_commissionProcessingLevelCodeCodeset | J102: level of processing comission | R102: CNIVCU | S102: OUI | T102: PRECOMP-PC21
A103: 250425200701 | C103: Context | D103: merchantParameters | E103: temp_conversionRate | F103: PercentageRate | J103: Conversion rate | N103: 72_DF01 part 8 | S103: OUI
A104: 250418220101 | B104: XXX | C104: Context | D104: merchantParameters | E104: temp_genericMerchandIdCheckCode | F104: temp_genericMerchandIdCheckCodeset | J104: Generic merchant id check code | R104: CEMIDG | S104: OUI | T104: PRECOMP-PC21
...

Sheet TypesStructures
A1: Structure | B1: Attributes | C1: Typologie | D1: Explication | E1: Commentaires
A2: AdditionalDataType | B2: complement | C2: Max255Text
A3: AdditionalDataType | B3: typeData | C3: Max50Text
A4: AdditionalDataType | B4: value | C4: Max3000Text
A5: AmountType | B5: amount | C5: ImpliedCurrencyAndAmount
A6: AmountType | B6: amountDescription | C6: Max35Text | D6: Short description of amount
A7: AmountType | B7: conversionDateTime | C7: ISODateTime
A8: AmountType | B8: currency | C8: ISO3NumericCurrencyCode
A9: AmountType | B9: exchangeRate | C9: Base25OneRate
A10: AmountType | B10: originalAmount | C10: ImpliedCurrencyAndAmount
A11: AmountType | B11: originalCurrency | C11: ISO3NumericCurrencyCode
A12: ContactType | B12: email | C12: Max256Text
A13: ContactType | B13: fax | C13: PhoneNumberText
A14: ContactType | B14: language | C14: ISOMax3ALanguageCode
A15: ContactType | B15: name | C15: Max70Text
A16: ContactType | B16: phone | C16: PhoneNumberText
A17: FeesType | B17: amount | C17: ImpliedCurrencyAndAmount
A18: FeesType | B18: conversionDateTime | C18: ISODateTime
... A21: FeesType | B21: exchangeRate | C21: Base25OneRate
A22: FeesType | B22: feesDescription | C22: Max35Text | D22: Short description of the Fee amount
A23: FeesType | B23: feesDescriptor | C23: Max35Text | D23: Identification of specific fee
A24: FeesType | B24: feesNature | C24: FeesNatureCodeset
A25: FeesType | B25: feesOtherNature | C25: Max35Text | D25: Additional information for specify the type of fee
A26: FeesType | B26: feesProgram | C26: Max35Text | D26: Identification of fee program
A27: FeesType | B27: originalCurrency | C27: ISO3NumericCurrencyCode
A28: KeyValueType | B28: key | C28: Max70Text | D28: Universal usage with string
A29: KeyValueType | B29: value | C29: Max70Text | D29: Universal usage with string
A30: LimitType | B30: limitAmount | C30: ImpliedCurrencyAndAmount | D30: montant de la limite
A31: LimitType | B31: limitDescription | C31: Max35Text | D31: description de la limite
A32: LimitType | B32: limitId | C32: LimitTypeIDCodeset | D32: Identifiant de la limite
A33: MerchantIdType | B33: merchantId | C33: Max10NumericText | D33: Merchant Id
A34: MerchantIdType | B34: merchantIdUsage | C34: MerchantIdUsageCodeset | D34: Merchant Id Usage (Internal, External, CB, Visa, MC)
A35: MerchantIdType | B35: merchantName | C35: Max40Text | D35: Merchant Name
A36: PhoneNumberType | B36: phoneNumber | C36: PhoneNumberText | D36: Première partie du : ^\+?[1-9]\d{1,14}$ selon le standard international E.164
A37: PointOfSaleType | B37: id | C37: Min7Max15NumericText | D37: Identifiant
A38: PointOfSaleType | B38: name | C38: Max40Text | D38: Name
A39: PointOfSaleType | B39: postalAddress | C39: PostalAddressType | D39: Postal Address
... A53: PostalAddressType | B53: townName | C53: Max70Text | D53: Nom de la ville
A54: ProcessorCardDataType | B54: cardLevel | C54: CardLevelCodeset
A55: ProcessorCardDataType | B55: cardUsage | C55: CardUsageCodeset
A56: ProcessorIssuerDataType | B56: issuerPlace | C56: IssuerPlaceCodeset
A57: ProcessorIssuerDataType | B57: issuerZone | C57: IssuerZoneCodeset
A58: SchemeFeesType | B58: amount | C58: AmountType | D58: Fixed amount or calculated amount proportional to the operation (rate)
A59: SchemeFeesType | B59: billingId | C59: Max20Text | D59: The billing identifier for the ICS (as appering on the invoice) | E59: Estimation, max 20
A60: SchemeFeesType | B60: rechargeable | C60: TrueFalseIndicator | D60: Yes the billing fee is directly chargeable to the merchant
A61: SchemeFeesType | B61: regionApplied | C61: MastercardRegionCodeset | D61: World region, Mastercard specific | E61: "ASPA", "CNDA", …...
A62: SchemeFeesType | B62: schemeFeesAmount | C62: AmountType | D62: Amount when scheme fee is expressed as amount (in settlement currency)
A63: SchemeFeesType | B63: schemeFeesAmountNature | C63: SchemeFeesAmountNatureCodeset | D63: For fee expressed as amount, specify whether it corresponds to floor, a cap, or by default fixed (an amount without particular meaning) | E63: FIXD=fixed (default), MINI=minimum, MAXI=maximum
A64: SchemeFeesType | B64: schemeFeesCaterory | C64: SchemeFeesCategoryCodeset | D64: Scheme Fee breakdown by category (bank typology) | E64: Operation, Licence, Processing, Subscription, Penalties
A65: SchemeFeesType | B65: schemeFeesGroup | C65: Max30Text | D65: ICS scheme category
A66: SchemeFeesType | B66: schemeFeesLabel | C66: Max70Text | D66: ICS short description for the fee | E66: Descruiption courte permettent de comprendre le fee
A67: SchemeFeesType | B67: schemeFeesMode | C67: SchemeFeesModeCodeset | D67: Either Standard direct rate/amount, or applied per region or applied by range depending on actual volume | E67: "Standard", "Region", "Tiered" & "-based"
A68: SchemeFeesType | B68: schemeFeesNature | C68: SchemeFeesNatureCodeset | D68: Quantity-based (amount or number) or Amount-based (% rate or bps (e.g 0,01% = 0,0001 $ Base Point)) | E68: Type n'est pas autorisé dans le nom de l'attribut
A69: SchemeFeesType | B69: schemeFeesRate | C69: Base25OneRate | D69: % Rate when scheme fee is expressed as rate
A70: SchemeFeesType | B70: tieredRangeAppliedHigh | C70: Max19Text | D70: Range upper value, inclusive | E70: Bornes gérées par l'application
A71: SchemeFeesType | B71: tieredRangeAppliedLow | C71: Max19Text | D71: Range lower value, inclusive | E71: Bornes gérées par l'application
A72: SchemeFeesType | B72: tieredVolume | C72: Max19Text | D72: Volume taken into account for selecting a tange | E72: Bornes gérées par l'application
A73: temp_ParametersAcquirerTelecommunicationCategoryType | B73: temp_accessIdentifier | C73: Exact20Text | D73: Access identifier
A74: temp_ParametersAcquirerTelecommunicationCategoryType | B74: temp_domainName | C74: Exact40Text | D74: Domain name
A75: temp_ParametersAcquirerTelecommunicationCategoryType | B75: temp_networkAddressingType | C75: temp_networkAddressingTypeCodeset | D75: Network addressing type
A76: temp_ParametersAcquirerTelecommunicationCategoryType | B76: temp_networkaddressOf theAcquirerSystemOrDns | C76: Exact20HexBinaryText | D76: Network address of the acquirer system or DNS
A77: temp_ParametersAcquirerTelecommunicationCategoryType | B77: temp_pADType | C77: temp_pADTypeCodeset | D77: PAD type
A78: temp_ParametersAcquirerTelecommunicationCategoryType | B78: temp_password | C78: Exact20Text | D78: Password
A79: temp_ParametersAcquirerTelecommunicationCategoryType | B79: temp_priorityAccessToAnAcquirerSystem | C79: temp_priorityAccessToAnAcquirerSystemCodeset | D79: Priority access to an acquirer system
A80: temp_ParametersAcquirerTelecommunicationCategoryType | B80: temp_telephoneNumberForNetworkAccess | C80: Exact20Text | D80: Telephone number for network access

Sheet TypesSimples
A1: Libellés | B1: Définiton | C1: Type | D1: Pattern | E1: FractionD | F1: TotalD | G1: minLength /mininclusive | H1: maxLength | I1: Commentaire
A2: 4Or6NumericText | B2: Number of objects represented as a positive integer. | C2: string | D2: ([0-9]{4}|[0-9]{6})
A3: Base25OneRate | B3: Rate expressed as a decimal | C3: string | D3: [0-9]{1,25}(\.?[0-9]{0,13})? | I3: 25 max avant la virgule et 13 max après la virgule
A4: DecimalRate | B4: decimal Amount | C4: string | D4: [0-9]{1,8}(\.?[0-9]{0,7})? | I4: 8 max avant la virgule et 7 max après la virgule
A5: Exac12AlphaNumericText | B5: 12 alphanumeric characters | C5: string | D5: [0-9A-Za-z]{12}
A6: Exact10AlphaNumericText | B6: 10 alphanumeric characters | C6: string | D6: [0-9A-Za-z]{10}
A7: Exact10NumericText | B7: Specifies a numeric string with an exact length of 10 digits. | C7: string | D7: [0-9]{10}
A8: Exact10Text | B8: 10 alphanumeric and special characters | C8: string | G8: 10 | H8: 10
A9: Exact11NumericText | B9: Specifies a numeric string with an exact length of 11 digits. | C9: string | D9: [0-9]{11}
A10: Exact11Text | B10: 11 alphanumeric and special characters | C10: string | G10: 11 | H10: 11
A11: Exact12AlphaNumericText | B11: 12 alphanumeric characters | C11: string | D11: [0-9A-Za-z]{12}
A12: Exact12NumericText | B12: Specifies a numeric string with an exact length of 12 digits. | C12: string | D12: [0-9]{12}
A13: Exact12Text | B13: 12 alphanumeric and special characters | C13: string | G13: 12 | H13: 12
A14: Exact15AlphaNumericText | B14: 15 alphanumeric characters | C14: string | D14: [0-9A-Za-z]{15}
A15: Exact15HexBinaryText | B15: Specifies a character string with an exact length of 15 binary bytes (30 hexadecimal text characters) | C15: string | D15: ([0-9A-F][0-9A-F]){15}
A16: Exact15Text | B16: 15 alphanumeric and special characters | C16: string | G16: 15 | H16: 15
A17: Exact16AlphaNumericText | B17: 16 alphanumeric characters | C17: string | D17: [0-9A-Za-z]{16}
A18: Exact16HexBinaryText | B18: Specifies a character string with an exact length of 16 binary bytes (32 hexadecimal text characters) | C18: string | D18: ([0-9A-F][0-9A-F]){16}
A19: Exact16NumericText | B19: Specifies a numeric string with an exact length of 16 digits. | C19: string | D19: [0-9]{16}
A20: Exact16Text | B20: 16 alphanumeric and special characters | C20: string | G20: 16 | H20: 16
A21: Exact19AlphaNumericText | B21: 19 alphanumeric characters | C21: string | D21: [0-9A-Za-z]{19}
A22: Exact19HexBinaryText | B22: Specifies a character string with an exact length of 19 binary bytes (38 hexadecimal text characters) | C22: string | D22: ([0-9A-F][0-9A-F]){19}
A23: Exact1AlphaNumericText | B23: 1 alphanumeric character | C23: string | D23: [0-9A-Za-z]{1}
A24: Exact1HexBinaryText | B24: Specifies a character string with an exact length of 1 binary bytes (2 hexadecimal text characters) | C24: string | D24: ([0-9A-F][0-9A-F]){1}
A25: Exact1NumericText | B25: Specifies a numeric string with an exact length of 1 digits. | C25: string | D25: [0-9]{1}
A26: Exact1Text | B26: Specifies a string with an exact length of 1 character | C26: string | G26: 1 | H26: 1
A27: Exact20HexBinaryText | B27: Specifies a character string with an exact length of 20 binary bytes (40 hexadecimal text characters) | C27: string | D27: ([0-9A-F][0-9A-F]){20}
A28: Exact20Text | B28: 20 alphanumeric and special characters | C28: string | G28: 20 | H28: 20
A29: Exact24Text | B29: 24 alphanumeric and special characters | C29: string | G29: 24 | H29: 24
A30: Exact252HexBinaryText | B30: Specifies a character string with an exact length of 252 binary bytes (504 hexadecimal text characters) | C30: string | D30: ([0-9A-F][0-9A-F]){252}
A31: Exact2AlphaNumericText | B31: 2 alphanumeric characters | C31: string | D31: [0-9A-Za-z]{2}
A32: Exact2HexBinaryText | B32: Specifies a character string with an exact length of 2 binary bytes (4 hexadecimal text characters) | C32: string | D32: ([0-9A-F][0-9A-F]){2}
A33: Exact2NumericText | B33: Specifies a numeric string with an exact length of 2 digits. | C33: string | D33: [0-9]{2}
A34: Exact2Text | B34: 2 alphanumeric and special characters | C34: string | G34: 2 | H34: 2
A35: Exact32Text | B35: 32 alphanumeric and special characters | C35: string | G35: 32 | H35: 32
A36: Exact36Text | B36: 36 alphanumeric and special characters | C36: string | G36: 36 | H36: 36
A37: Exact3AlphaNumericText | B37: 3 alphanumeric characters | C37: string | D37: [0-9A-Za-z]{3}
A38: Exact3HexBinaryText | B38: Specifies a character string with an exact length of 3 binary bytes (6 hexadecimal text characters) | C38: string | D38: ([0-9A-F][0-9A-F]){3}
A39: Exact3NumericText | B39: Specifies a numeric string with an exact length of 3 digits. | C39: string | D39: [0-9]{3}
A40: Exact3Text | B40: 3 alphanumeric and special characters | C40: string | G40: 3 | H40: 3
A41: Exact40Text | B41: Month within a particular calendar year represented by YYYY-MM (ISO 8601). | C41: string | G41: 40 | H41: 40
A42: Exact4AlphaNumericText | B42: 4 alphanumeric characters | C42: string | D42: [0-9A-Za-z]{4}
A43: Exact4HexBinaryText | B43: Specifies a character string with an exact length of 4 binary bytes (8 hexadecimal text characters) | C43: string | D43: ([0-9A-F][0-9A-F]){4}
A44: Exact4NumericText | B44: Specifies a numeric string with an exact length of 4 digits. | C44: string | D44: [0-9]{4}
A45: Exact4Text | B45: 4 alphanumeric and special characters | C45: string | G45: 4 | H45: 4
A46: Exact5HexBinaryText | B46: Specifies a character string with an exact length of 5 binary bytes (10 hexadecimal text characters) | C46: string | D46: ([0-9A-F][0-9A-F]){5}
A47: Exact5NumericText | B47: Specifies a numeric string with an exact length of 5 digits. | C47: string | D47: [0-9]{5}
A48: Exact6NumericText | B48: Specifies a numeric string with an exact length of 6 digits. | C48: string | D48: [0-9]{6}
A49: Exact6Text | B49: 6 alphanumeric and special characters | C49: string | G49: 6 | H49: 6
A50: Exact7AlphaNumericText | B50: Specifies a alphanumeric string with a minlength of 1 and maxlength of 7 digits | C50: string | D50: [0-9]{1,7}
A51: Exact7HexBinaryText | B51: Specifies a character string with an exact length of 7 binary bytes (14 hexadecimal text characters) | C51: string | D51: ([0-9A-F][0-9A-F]){7}
A52: Exact8AlphaNumericText | B52: 8 alphanumeric characters | C52: string | D52: [0-9A-Za-z]{8}
A53: Exact8HexBinaryText | B53: Specifies a character string with an exact length of 8 binary bytes (16 hexadecimal text characters) | C53: string | D53: ([0-9A-F][0-9A-F]){8}
A54: Exact8NumericText | B54: Specifies a numeric string with an exact length of 8 digits. | C54: string | D54: [0-9]{8}
A55: Exact8Text | B55: 8 alphanumeric and special characters | C55: string | G55: 8 | H55: 8
A56: IBANIdentifier | B56: The International Bank Account Number is a code used internationally by financial institutions to uniquely identify the account of a customer at a financial institution as described in the 2007 edition of the ISO 13616 standard Banking and related financial services International Bank Account Number (IBAN) and replaced by the more recent edition of the standard. | C56: string | D56: [A-Z]{2,2}[0-9]{2,2}[a-zA-Z0-9]{1,30}
A57: ImpliedCurrencyAndAmount | B57: Number of monetary units specified in a currency where the unit of currency is implied by the context and compliant with ISO 4217. The decimal separator is a dot. | C57: string | D57: \-?[0-9]{1,18}(\.?[0-9]{0,5})? | I57: Examples : 12.3 / -5.01 / 15.12345 / -123456.12345 Definition : CAPE et ATICA Number of monetary units specified in a currency where the unit of currency is implied by the context and compliant with ISO 4217. The decimal separator is a dot. Note: a zero amount is considered a positive amount. Format : minInclusive 0 / totalDigits 18 / fractionDigits 5
A58: ISO18245MerchantCategoryCode | B58: Code used to enable the classification of merchants into specific categories. (ISO 18245). | C58: string | D58: [0-9]{4,4} | I58: Code used to enable the classification of merchants into specific categories based on the type of business, trade or services supplied. Values are specified only for those merchant categories that are generally expected to originate retail financial transactions (ISO 18245). The code is checked against the list of merchant categories coded with four digit characters, defined in the standar
A59: ISO2AlphaNumericCountryCode | B59: Code to identify a country, a dependency, or another area of particular geopolitical interest (ISO 3166, Text -2 code) | C59: string | D59: [A-Z]{2,2}
A60: ISO3AlphabeticCurrencyCode | B60: Code to identify the Currency | C60: string | D60: [0-9]{3,3}
A61: ISO3AlphaNumericCurrencyCode | B61: Code to identify the Currency (ISO 4217) | C61: string | D61: [A-Z]{3,3}
A62: ISO3NumericCountryCode | B62: Code to identify a country, a dependency, or another area of particular geopolitical interest (ISO 3166, Numeric-3 code) | C62: string | D62: [0-9]{3,3} | I62: Code to identify a country, a dependency, or another area of particular geopolitical interest, on the basis of country names obtained from the United Nations (ISO 3166, Numeric-3 code). The code is checked against the list of country names coded with three digit characters, defined in the standard.
A63: ISO3NumericCurrencyCode | B63: Code to identify the Currency (ISO 4217) | C63: string | D63: [0-9]{3,3}
A64: ISOCountrySubdivisionCode | B64: Code to identify an area of geopolitical interest, based on names obtained from the United Nations ISO 3166-2 or the local authority | C64: string | D64: [A-Z]{2,3} | I64: ISO 3166-2
A65: ISODate | B65: Date within a particular calendar year represented by YYYY-MM-DD (ISO 8601). | C65: string | D65: ([0-9]{4})-(1[0-2]|0[1-9])-(3[01]|0[1-9]|[12][0-9]) | I65: Format : YYYY-MM-DD ; Example 2024-12-31
A66: ISODateTime | B66: The dateTime is specified in the following form <YYYY-MM-DDThh:mm:ss> | C66: string | D66: (-?(?:[1-9][0-9]*)?[0-9]{4})-(1[0-2]|0[1-9])-(3[01]|0[1-9]|[12][0-9])T(2[0-3]|[01][0-9]):([0-5][0-9]):([0-5][0-9])(\.[0-9]+)?(Z|[+-](?:2[0-3]|[01][0-9]):[0-5][0-9])? | I66: Definition: A particular point in the progression of time defined by a mandatory date and a mandatory time component - Voir onglet ISODateTime
A67: ISOMax3ALanguageCode | B67: Identification of the language name in accordance with ISO 639-1 and ISO 639-2. | C67: string | D67: [a-z]{2,3} | I67: Identification of the language name in accordance with ISO 639-1 and ISO 639-2. The type is validated by the list of values coded with two or three alphabetic characters, defined in the standard.
A68: ISOYearMonth | B68: Month within a particular calendar year represented by YYYY-MM (ISO 8601). | C68: string | D68: ([0-9]{4})-(1[0-2]|0[1-9]) | I68: Format : YYYY-MM ; Example 2024-12
A69: Max100Text | B69: Specifies a character string with a minlength of 1 and maxlength of 100 characters. | C69: string | G69: 1 | H69: 100
A70: Max10AlphaNumericText | B70: Specifies an alphanumeric string with a minlength of 1 and maxlength of 10 digits | C70: string | D70: [0-9A-Za-z]{1,10}
A71: Max10NumericText | B71: Specifies a numeric string with a minlength of 1 and maxlength of 10 digits. | C71: string | D71: [0-9]{1,10}
A72: Max10Text | B72: Specifies a character string with a minlength of 1 and maxlength of 10 characters. | C72: string | G72: 1 | H72: 10
A73: Max11NumericText | B73: Specifies a numeric string with a minlength of 1 and maxlength of 11 digits. | C73: string | D73: [0-9]{1,11}
A74: Max128HexBinaryText | B74: Specifies a character string with a maximum length of 128 binary bytes (256 hexadecimal text characters) | C74: string | D74: ([0-9A-F][0-9A-F]){1,128}
A75: Max12Text | B75: Specifies a character string with a minlength of 1 and maxlength of 12 characters | C75: string | G75: 1 | H75: 12
A76: Max13AlphaNumericText | B76: Specifies a alphanumeric string with a minlength of 1 and maxlength of 13 digits | C76: string | D76: [0-9]{1,13}
A77: Max14AlphaNumericText | B77: Specifies a alphanumeric string with a minlength of 1 and maxlength of 14 digits | C77: string | D77: [0-9]{1,14}
A78: Max14NumericText | B78: Specifies a numeric string with a minlength of 1 and maxlength of 14 digits | C78: string | D78: [0-9]{1,14}
A79: Max150HexBinaryText | B79: Specifies a character string with a maximum length of 150 binary bytes (300 hexadecimal text characters) | C79: string | D79: ([0-9A-F][0-9A-F]){1,150}
A80: Max15Text | B80: Specifies a character string with a minlength of 1 and maxlength of 15 characters. | C80: string | G80: 1 | H80: 15
A81: Max16Text | B81: Specifies a character string with a minlength of 1 and maxlength of 16 characters. | C81: string | G81: 1 | H81: 16
A82: Max17Text | B82: Specifies a character string with a minlength of 1 and maxlength of 17 characters. | C82: string | G82: 1 | H82: 17
A83: Max19AlphaNumericText | B83: Specifies an alphanumeric string with a minlength of 1 and maxlength of 19 digits | C83: string | D83: [0-9A-Za-z]{1,19}
A84: Max19HexBinaryText | B84: Specifies a character string with a maximum length of 19 binary bytes (38 hexadecimal text characters) | C84: string | D84: ([0-9A-F][0-9A-F]){1,19}
A85: Max19NumericText | B85: Specifies a numeric string with minlength of 1 and a maxlength of 19 digits. | C85: string | D85: [0-9]{1,19}
A86: Max19Text | B86: Specifies a character string with a minlength of 1 and maxlength of 19 characters. | C86: string | G86: 1 | H86: 19
A87: Max200Text | B87: Specifies a character string with a minlength of 1 and maxlength of 200 characters. | C87: string | G87: 1 | H87: 200
A88: Max20Text | B88: Specifies a character string with a minlength of 1 and maxlength of 20 characters. | C88: string | G88: 1 | H88: 20
A89: Max23HexBinaryText | B89: Specifies a character string with a maximum length of 23 binary bytes (46 hexadecimal text characters) | C89: string | D89: ([0-9A-F][0-9A-F]){1,23}
A90: Max248HexBinaryText | B90: Specifies a character string with a maximum length of 258 binary bytes (516 hexadecimal text characters) | C90: string | D90: ([0-9A-F][0-9A-F]){1,258}
A91: Max24HexBinaryText | B91: Specifies a character string with a maximum length of 24 binary bytes (48 hexadecimal text characters) | C91: string | D91: ([0-9A-F][0-9A-F]){1,23}
A92: Max252HexBinaryText | B92: Specifies a character string with a maximum length of 252 binary bytes (504 hexadecimal text characters) | C92: string | D92: ([0-9A-F][0-9A-F]){1,252}
A93: Max255HexBinaryText | B93: Specifies a character string with a maximum length of 255 binary bytes (510 hexadecimal text characters) | C93: string | D93: ([0-9A-F][0-9A-F]){1,255}
A94: Max255Text | B94: Specifies a character string with a minlength of 1 and maxlength of 255 characters | C94: string | G94: 1 | H94: 255
A95: Max256Text | B95: Specifies a character string with a minlength of 1 and maxlength of 256 characters | C95: string | G95: 1 | H95: 256
A96: Max26Text | B96: Specifies a character string with a minlength of 1 and maxlength of 26 characters | C96: string | G96: 1 | H96: 26
A97: Max29AlphaNumericText | B97: Specifies an alphanumeric string with a minlength of 1 and maxlength of 29 digits. | C97: string | D97: [0-9A-Za-z]{1,29}
A98: Max2AlphaNumericText | B98: Specifies an alphanumeric string with a minlength of 1 and maxlength of 2 digits | C98: string | D98: [0-9A-Za-z]{1,2}
A99: Max2KHexBinaryText | B99: Specifies a character string with a maximum length of 2048 binary bytes (4096 hexadecimal text characters) | C99: string | D99: ([0-9A-F][0-9A-F]){1,2048}
A100: Max2NumericText | B100: Specifies a numeric string with a minlength of 1 and maxlength of 2 digits | C100: string | D100: [0-9]{1,2}
...

Sheet Codeset
A1: CODE SET - LISTE DE VALEURS AUTORISEES POUR LE TYPE DE CHAMP
A2: Code Set | B2: Format | C2: Data | D2: Data Comment
A3: AcceptanceChannelCodeset | B3: Exact4Text | C3: FFPM | D3: Face to face payment
A4: AcceptanceChannelCodeset | B4: Exact4Text | C4: RMPM | D4: Remote payment
A5: AcceptanceChannelCodeset | B5: Exact4Text | C5: UTPM | D5: Unattended payment
A6: AcceptanceSystemCurrentConnectingModeCodeset | B6: Exact4Text | C6: LAIP | D6: LAN IP
A7: AcceptanceSystemCurrentConnectingModeCodeset | B7: Exact4Text | C7: RTIP | D7: RTC NAS IP
A8: AcceptanceSystemCurrentConnectingModeCodeset | B8: Exact4Text | C8: RTPA | D8: RTC PAD X25
A9: AcceptanceSystemCurrentConnectingModeCodeset | B9: Exact4Text | C9: DELI | D9: X25 dedicated line
A10: AcceptanceSystemCurrentConnectingModeCodeset | B10: Exact4Text | C10: RNBC | D10: RNIS B canal (EBS)
A11: AcceptanceSystemCurrentConnectingModeCodeset | B11: Exact4Text | C11: RNDC | D11: RNIS D canal X25
A12: AcceptanceSystemCurrentConnectingModeCodeset | B12: Exact4Text | C12: GSMX | D12: GSM X25
A13: AcceptanceSystemCurrentConnectingModeCodeset | B13: Exact4Text | C13: GSMI | D13: GSM IP
... A113: AuthorisationForcingCodeCodeset | B113: Exact4Text | C113: NOFO | D113: No forcing
A114: BlacklistDistributionRegionsCodeset | B114: Exact2Text | C114: RZ
A115: BlacklistDistributionRegionsCodeset | B115: Exact2Text | C115: RD
A116: BlacklistDistributionRegionsCodeset | B116: Exact2Text | C116: RN
A117: BlockingReasonCodeset | B117: Max50Text | C117: BLOCKING_REASON_1
A118: BlockingReasonCodeset | B118: Max50Text | C118: BLOCKING_REASON_2
A119: BlockingRegulatoryReasonCodeset | B119: Max50Text | C119: REG_BLOCKING_REASON_1
A120: BlockingRegulatoryReasonCodeset | B120: Max50Text | C120: REG_BLOCKING_REASON_2
A121: BrandCodeset | B121: Exact4Text | C121: CBFR | D121: CB
A122: BrandCodeset | B122: Exact4Text | C122: VISA | D122: VISA
A123: BrandCodeset | B123: Exact4Text | C123: MACD | D123: Mastercard
A124: BrandCodeset | B124: Exact4Text | C124: DISC | D124: Discover
A125: BrandCodeset | B125: Exact4Text | C125: UPIC | D125: UPI
A126: BrandCodeset | B126: Exact4Text | C126: VPAY | D126: VPAY
A127: BrandCodeset | B127: Exact4Text | C127: ELEC | D127: Electron
A128: BrandCodeset | B128: Exact4Text | C128: MSTR | D128: Maestro
A129: BrandCodeset | B129: Exact4Text | C129: JCB0 | D129: JCB
A130: BrandCodeset | B130: Exact4Text | C130: REPV | D130: Reserved for private use
A131: BuyingMethodCodeset | B131: Exact4Text | C131: INAP | D131: In-app payment
A132: BuyingMethodCodeset | B132: Exact4Text | C132: BRWS | D132: Browser-based payment
... A135: CardAcceptorArchitectureCategoryCodeset | B135: Exact4Text | C135: DICL | D135: Distributed (clustered)
A136: CardAgreementDeferredCalendarCodeset | B136: Max50Text | C136: LAST_DAY_ON_MONTH
A137: CardAgreementDeferredCalendarCodeset | B137: Max50Text | C137: FIRST_DAY_ON_MONTH
A138: CardAgreementDeferredCalendarCodeset | B138: Max50Text | C138: MIDDLE_DAY_ON_MONTH
A139: CardApplicationCodeset | B139: Exact4Text | C139: EMVC | D139: EMV
A140: CardApplicationCodeset | B140: Exact4Text | C140: CIMG | D140: Contactless integrated circuit - magstripe context
A141: CardDataEntryModeCodeset | B141: Exact4Text | C141: NOTS | D141: Not specified
A142: CardDataEntryModeCodeset | B142: Exact4Text | C142: MAGS | D142: Magstripe
A143: CardDataEntryModeCodeset | B143: Exact4Text | C143: CCEC | D143: Contactless chip transaction using EMV chip data
A144: CardDataEntryModeCodeset | B144: Exact4Text | C144: CCMD | D144: Contactless chip transaction using magstripe data
A145: CardDataEntryModeCodeset | B145: Exact4Text | C145: ICCR | D145: Integrated circuit card reader
A146: CardDataEntryModeCodeset | B146: Exact4Text | C146: MANE | D146: Manual entry
A147: CardDataEntryModeCodeset | B147: Exact4Text | C147: MAAR | D147: Magstripe, after attempt to read chip
A148: CardDataEntryModeCodeset | B148: Exact4Text | C148: PVBS | D148: Provided by a server
A149: CardDataEntryModeCodeset | B149: Exact4Text | C149: COFT | D149: Card-on-File
A150: CardDesignCodeset | B150: Max50Text | C150: WORLD_CUP_FOOTBALL_2023
A151: CardDesignCodeset | B151: Max50Text | C151: WORLD_CUP_FOOTBALL_2026
A152: CardholderAddressCheckingInformationCodeset | B152: Exact4Text | C152: PAFM | D152: Postcode and address fully match
A153: CardholderAddressCheckingInformationCodeset | B153: Exact4Text | C153: PAPM | D153: Postcode and address partially match
A154: CardholderAddressCheckingInformationCodeset | B154: Exact4Text | C154: PANM | D154: Postcode and address do not match
A155: CardholderAddressCheckingInformationCodeset | B155: Exact4Text | C155: NPAD | D155: Control was not performed or was not performed for all data elements
A156: CardholderAddressCheckingInformationCodeset | B156: Exact4Text | C156: RTRY | D156: Retry (indeterminate outcome)
A157: CardholderAuthenticationCapabilitiesCodeset | B157: Exact4Text | C157: NOEA | D157: No electronic authentication
A158: CardholderAuthenticationCapabilitiesCodeset | B158: Exact4Text | C158: AUTP | D158: Authentication by PIN
A159: CardholderAuthenticationCapabilitiesCodeset | B159: Exact4Text | C159: EAOS | D159: Electronic analysis of signature
A160: CardholderAuthenticationCapabilitiesCodeset | B160: Exact4Text | C160: OTHR | D160: Other (default value)
A161: CardholderAuthenticationCapabilitiesCodeset | B161: Exact4Text | C161: RFPU | D161: Reserved for private use
A162: CardholderAuthenticationMethodCodeset | B162: Exact4Text | C162: NAUT | D162: No authentication
A163: CardholderAuthenticationMethodCodeset | B163: Exact4Text | C163: PINE | D163: PIN
... A225: CompanyRegistrationNumberCategoryCodeset | B225: Exact4Text | C225: INTS | D225: International Identification (TVA intercommunautaire)
A226: ContactlessActivationChoiceCodeset | B226: Max50Text | C226: ACTIVE
A227: ContactlessActivationChoiceCodeset | B227: Max50Text | C227: INACTIVE
A228: ContactlessActivationChoiceCodeset | B228: Max50Text | C228: NO_NOTICE
A229: ContractCategoryCodeset | B229: Exact2Text | C229: CB | D229: Paiement et retrait guichet
A230: ContractCategoryCodeset | B230: Exact2Text | C230: DC | D230: DCC
A231: ContractCategoryCodeset | B231: Exact2Text | C231: CP | D231: CUP
A232: ContractCategoryCodeset | B232: Exact2Text | C232: DF | D232: DFS
A233: ContractCategoryCodeset | B233: Exact2Text | C233: JC | D233: JCB
A234: CountryZoneCodeset | B234: Exact4Text | C234: FRDT | D234: France & DOM-TOM
A235: CountryZoneCodeset | B235: Exact4Text | C235: EURO | D235: Europe (without France & DOM-TOM)
A236: CountryZoneCodeset | B236: Exact4Text | C236: AFRC | D236: Africa
A237: CountryZoneCodeset | B237: Exact4Text | C237: NOAM | D237: North America
A238: CountryZoneCodeset | B238: Exact4Text | C238: SOAM | D238: South America
A239: CountryZoneCodeset | B239: Exact4Text | C239: ASIA | D239: Asia
A240: CountryZoneCodeset | B240: Exact4Text | C240: OCEA | D240: Océania
... A363: LimitTypeIDCodeset | B363: Max50Text | C363: EXCEPRETR | D363: retrait exceptionel
A364: LimitTypeIDCodeset | B364: Max50Text | C364: GLOBMENS
A365: LimitTypeIDCodeset | B365: Max50Text | C365: PAIEMINT7J | D365: paiement international sur 7j
A366: LimitTypeIDCodeset | B366: Max50Text | C366: PAIEMNAT7J | D366: paiement national sur 7j
A367: LimitTypeIDCodeset | B367: Max50Text | C367: RETRBQE1J | D367: retrait banque par jour
A368: LimitTypeIDCodeset | B368: Max50Text | C368: RETRINT3J | D368: retrait international sur 3j
A369: LimitTypeIDCodeset | B369: Max50Text | C369: RETRNAT3J | D369: retrait national sur 3j
A370: LockingReasonCodeset | B370: Max50Text | C370: LOCKING_REASON_1
A371: LockingReasonCodeset | B371: Max50Text | C371: LOCKING_REASON_2
A372: LockingReasonCodeset | B372: Max50Text | C372: LOCKING_REASON_3
A373: LockingReasonCodeset | B373: Max50Text | C373: LOCKING_REASON_4
A374: LockingReasonCodeset | B374: Max50Text | C374: LOCKING_REASON_5
A375: MaskGeneratorAlgorithmCodeset | B375: Max12Text | C375: MGF1-SHA256 | D375: Generator Function, used for RSA encryption and RSA igital signature (PKCS #1 version 2.1) - (ASN.1 Object Identifier: id-mgf1). Message digest algorithm SHA-256 as defined in FIPS 180-1 and 2 - (ASN.1 Object Identifier: id-sha256).
A376: MaskGeneratorAlgorithmCodeset | B376: Max12Text | C376: MGF1-SHA384 | D376: Generator Function, used for RSA encryption and RSA igital signature (PKCS #1 version 2.1) - (ASN.1 Object Identifier: id-mgf1). Message digest algorithm SHA-384 as defined in FIPS 180-1 and 2 - (ASN.1 Object Identifier: id-sha384).
A377: MaskGeneratorAlgorithmCodeset | B377: Max12Text | C377: MGF1-SHA512 | D377: Generator Function, used for RSA encryption and RSA igital signature (PKCS #1 version 2.1) - (ASN.1 Object Identifier: id-mgf1). Message digest algorithm SHA-512 as defined in FIPS 180-1 and 2 - (ASN.1 Object Identifier: id-sha512).
A378: MaskGeneratorAlgorithmCodeset | B378: Max12Text | C378: MGF1-SHA1 | D378: Generator Function, used for RSA encryption and RSA igital signature (PKCS #1 version 2.1) - (ASN.1 Object Identifier: id-mgf1). The DEPRECATED Message digest algorithm SHA-1 as defined in FIPS 180-1 - (ASN.1 Object Identifier: id-sha1).
A379: MastercardRegionCodeset | B379: Exact4Text | C379: ASPA | D379: Asia Pacific
A380: MastercardRegionCodeset | B380: Exact4Text | C380: CNDA | D380: Canada
A381: MastercardRegionCodeset | B381: Exact4Text | C381: DMST | D381: Domestic
A382: MastercardRegionCodeset | B382: Exact4Text | C382: EUNS | D382: EU non SEPA
A383: MastercardRegionCodeset | B383: Exact4Text | C383: EUSE | D383: EU SEPA
A384: MastercardRegionCodeset | B384: Exact4Text | C384: LACA | D384: Latine American Central
...

Sheet DICO_NomsCourts
A2: Objet-N0 - Nom long | B2: Objet-N1 - Nom long | C2: Objet-N2 - Nom long | D2: Objet-N3 - Nom long | E2: Objet_N0 - Nom Court | F2: Objet_N1 - Nom Court | G2: Objet_N2 - Nom Court | H2: Objet_N3 - Nom Court
A3: =DICO_Export!D3 -> error | B3: =DICO_Export!E3 -> code | C3: =#REF! -> #REF! | D3: =#REF! -> #REF! | E3: =LEFT(A3,1)&SUBSTITUTE(SUBSTITUTE(SUBSTITUTE(SUBSTITUTE(SUBSTITUTE(SUBSTITUTE(SUBSTITUTE(RIGHT(A3,LEN(A3)-1),"a"," "),"e"," "),"i"," "),"o"," "),"u"," "),"y"," ")," ","") -> errr | F3: =LEFT(B3,1)&SUBSTITUTE(SUBSTITUTE(SUBSTITUTE(SUBSTITUTE(SUBSTITUTE(SUBSTITUTE(SUBSTITUTE(RIGHT(B3,LEN(B3)-1),"a"," "),"e"," "),"i"," "),"o"," "),"u"," "),"y"," ")," ","") -> cd | G3: =LEFT(C3,1)&SUBSTITUTE(SUBSTITUTE(SUBSTITUTE(SUBSTITUTE(SUBSTITUTE(SUBSTITUTE(SUBSTITUTE(RIGHT(C3,LEN(C3)-1),"a"," "),"e"," "),"i"," "),"o"," "),"u"," "),"y"," ")," ","") -> #REF! | H3: =LEFT(D3,1)&SUBSTITUTE(SUBSTITUTE(SUBSTITUTE(SUBSTITUTE(SUBSTITUTE(SUBSTITUTE(SUBSTITUTE(RIGHT(D3,LEN(D3)-1),"a"," "),"e"," "),"i"," "),"o"," "),"u"," "),"y"," ")," ","") -> #REF!
A4: =DICO_Export!D4 -> error | B4: =DICO_Export!E4 -> developerText | C4: =#REF! -> #REF! | D4: =#REF! -> #REF! | E4: =LEFT(A4,1)&SUBSTITUTE(SUBSTITUTE(SUBSTITUTE(SUBSTITUTE(SUBSTITUTE(SUBSTITUTE(SUBSTITUTE(RIGHT(A4,LEN(A4)-1),"a"," "),"e"," "),"i"," "),"o"," "),"u"," "),"y"," ")," ","") -> errr | F4: =LEFT(B4,1)&SUBSTITUTE(SUBSTITUTE(SUBSTITUTE(SUBSTITUTE(SUBSTITUTE(SUBSTITUTE(SUBSTITUTE(RIGHT(B4,LEN(B4)-1),"a"," "),"e"," "),"i"," "),"o"," "),"u"," "),"y"," ")," ","") -> dvlprTxt | G4: =LEFT(C4,1)&SUBSTITUTE(SUBSTITUTE(SUBSTITUTE(SUBSTITUTE(SUBSTITUTE(SUBSTITUTE(SUBSTITUTE(RIGHT(C4,LEN(C4)-1),"a"," "),"e"," "),"i"," "),"o"," "),"u"," "),"y"," ")," ","") -> #REF! | H4: =LEFT(D4,1)&SUBSTITUTE(SUBSTITUTE(SUBSTITUTE(SUBSTITUTE(SUBSTITUTE(SUBSTITUTE(SUBSTITUTE(RIGHT(D4,LEN(D4)-1),"a"," "),"e"," "),"i"," "),"o"," "),"u"," "),"y"," ")," ","") -> #REF!
A5: =DICO_Export!D5 -> error | B5: =DICO_Export!E5 -> moreInfo | C5: =#REF! -> #REF! | D5: =#REF! -> #REF! | E5: =LEFT(A5,1)&SUBSTITUTE(SUBSTITUTE(SUBSTITUTE(SUBSTITUTE(SUBSTITUTE(SUBSTITUTE(SUBSTITUTE(RIGHT(A5,LEN(A5)-1),"a"," "),"e"," "),"i"," "),"o"," "),"u"," "),"y"," ")," ","") -> errr | F5: =LEFT(B5,1)&SUBSTITUTE(SUBSTITUTE(SUBSTITUTE(SUBSTITUTE(SUBSTITUTE(SUBSTITUTE(SUBSTITUTE(RIGHT(B5,LEN(B5)-1),"a"," "),"e"," "),"i"," "),"o"," "),"u"," "),"y"," ")," ","") -> mrInf | G5: =LEFT(C5,1)&SUBSTITUTE(SUBSTITUTE(SUBSTITUTE(SUBSTITUTE(SUBSTITUTE(SUBSTITUTE(SUBSTITUTE(RIGHT(C5,LEN(C5)-1),"a"," "),"e"," "),"i"," "),"o"," "),"u"," "),"y"," ")," ","") -> #REF! | H5: =LEFT(D5,1)&SUBSTITUTE(SUBSTITUTE(SUBSTITUTE(SUBSTITUTE(SUBSTITUTE(SUBSTITUTE(SUBSTITUTE(RIGHT(D5,LEN(D5)-1),"a"," "),"e"," "),"i"," "),"o"," "),"u"," "),"y"," ")," ","") -> #REF!
A6: =DICO_Export!D6 -> error | B6: =DICO_Export!E6 -> text | C6: =#REF! -> #REF! | D6: =#REF! -> #REF! | E6: =LEFT(A6,1)&SUBSTITUTE(SUBSTITUTE(SUBSTITUTE(SUBSTITUTE(SUBSTITUTE(SUBSTITUTE(SUBSTITUTE(RIGHT(A6,LEN(A6)-1),"a"," "),"e"," "),"i"," "),"o"," "),"u"," "),"y"," ")," ","") -> errr | F6: =LEFT(B6,1)&SUBSTITUTE(SUBSTITUTE(SUBSTITUTE(SUBSTITUTE(SUBSTITUTE(SUBSTITUTE(SUBSTITUTE(RIGHT(B6,LEN(B6)-1),"a"," "),"e"," "),"i"," "),"o"," "),"u"," "),"y"," ")," ","") -> txt | G6: =LEFT(C6,1)&SUBSTITUTE(SUBSTITUTE(SUBSTITUTE(SUBSTITUTE(SUBSTITUTE(SUBSTITUTE(SUBSTITUTE(RIGHT(C6,LEN(C6)-1),"a"," "),"e"," "),"i"," "),"o"," "),"u"," "),"y"," ")," ","") -> #REF! | H6: =LEFT(D6,1)&SUBSTITUTE(SUBSTITUTE(SUBSTITUTE(SUBSTITUTE(SUBSTITUTE(SUBSTITUTE(SUBSTITUTE(RIGHT(D6,LEN(D6)-1),"a"," "),"e"," "),"i"," "),"o"," "),"u"," "),"y"," ")," ","") -> #REF!
A7: =DICO_Export!D7 -> httpStatus | B7: =DICO_Export!E7 -> httpCode | C7: =#REF! -> #REF! | D7: =#REF! -> #REF! | E7: =LEFT(A7,1)&SUBSTITUTE(SUBSTITUTE(SUBSTITUTE(SUBSTITUTE(SUBSTITUTE(SUBSTITUTE(SUBSTITUTE(RIGHT(A7,LEN(A7)-1),"a"," "),"e"," "),"i"," "),"o"," "),"u"," "),"y"," ")," ","") -> httpStts | F7: =LEFT(B7,1)&SUBSTITUTE(SUBSTITUTE(SUBSTITUTE(SUBSTITUTE(SUBSTITUTE(SUBSTITUTE(SUBSTITUTE(RIGHT(B7,LEN(B7)-1),"a"," "),"e"," "),"i"," "),"o"," "),"u"," "),"y"," ")," ","") -> httpCd | G7: =LEFT(C7,1)&SUBSTITUTE(SUBSTITUTE(SUBSTITUTE(SUBSTITUTE(SUBSTITUTE(SUBSTITUTE(SUBSTITUTE(RIGHT(C7,LEN(C7)-1),"a"," "),"e"," "),"i"," "),"o"," "),"u"," "),"y"," ")," ","") -> #REF! | H7: =LEFT(D7,1)&SUBSTITUTE(SUBSTITUTE(SUBSTITUTE(SUBSTITUTE(SUBSTITUTE(SUBSTITUTE(SUBSTITUTE(RIGHT(D7,LEN(D7)-1),"a"," "),"e"," "),"i"," "),"o"," "),"u"," "),"y"," ")," ","") -> #REF!
A8: =DICO_Export!D8 -> httpStatus | B8: =DICO_Export!E8 -> requestId | C8: =#REF! -> #REF! | D8: =#REF! -> #REF! | E8: =LEFT(A8,1)&SUBSTITUTE(SUBSTITUTE(SUBSTITUTE(SUBSTITUTE(SUBSTITUTE(SUBSTITUTE(SUBSTITUTE(RIGHT(A8,LEN(A8)-1),"a"," "),"e"," "),"i"," "),"o"," "),"u"," "),"y"," ")," ","") -> httpStts | F8: =LEFT(B8,1)&SUBSTITUTE(SUBSTITUTE(SUBSTITUTE(SUBSTITUTE(SUBSTITUTE(SUBSTITUTE(SUBSTITUTE(RIGHT(B8,LEN(B8)-1),"a"," "),"e"," "),"i"," "),"o"," "),"u"," "),"y"," ")," ","") -> rqstId | G8: =LEFT(C8,1)&SUBSTITUTE(SUBSTITUTE(SUBSTITUTE(SUBSTITUTE(SUBSTITUTE(SUBSTITUTE(SUBSTITUTE(RIGHT(C8,LEN(C8)-1),"a"," "),"e"," "),"i"," "),"o"," "),"u"," "),"y"," ")," ","") -> #REF! | H8: =LEFT(D8,1)&SUBSTITUTE(SUBSTITUTE(SUBSTITUTE(SUBSTITUTE(SUBSTITUTE(SUBSTITUTE(SUBSTITUTE(RIGHT(D8,LEN(D8)-1),"a"," "),"e"," "),"i"," "),"o"," "),"u"," "),"y"," ")," ","") -> #REF!
A9: =DICO_Export!D9 -> cardContext | B9: =DICO_Export!E9 -> acquiringChannel | C9: =#REF! -> #REF! | D9: =#REF! -> #REF! | E9: =LEFT(A9,1)&SUBSTITUTE(SUBSTITUTE(SUBSTITUTE(SUBSTITUTE(SUBSTITUTE(SUBSTITUTE(SUBSTITUTE(RIGHT(A9,LEN(A9)-1),"a"," "),"e"," "),"i"," "),"o"," "),"u"," "),"y"," ")," ","") -> crdCntxt | F9: =LEFT(B9,1)&SUBSTITUTE(SUBSTITUTE(SUBSTITUTE(SUBSTITUTE(SUBSTITUTE(SUBSTITUTE(SUBSTITUTE(RIGHT(B9,LEN(B9)-1),"a"," "),"e"," "),"i"," "),"o"," "),"u"," "),"y"," ")," ","") -> acqrngChnnl | G9: =LEFT(C9,1)&SUBSTITUTE(SUBSTITUTE(SUBSTITUTE(SUBSTITUTE(SUBSTITUTE(SUBSTITUTE(SUBSTITUTE(RIGHT(C9,LEN(C9)-1),"a"," "),"e"," "),"i"," "),"o"," "),"u"," "),"y"," ")," ","") -> #REF! | H9: =LEFT(D9,1)&SUBSTITUTE(SUBSTITUTE(SUBSTITUTE(SUBSTITUTE(SUBSTITUTE(SUBSTITUTE(SUBSTITUTE(RIGHT(D9,LEN(D9)-1),"a"," "),"e"," "),"i"," "),"o"," "),"u"," "),"y"," ")," ","") -> #REF!
A10: =DICO_Export!D10 -> cardContext | B10: =DICO_Export!E10 -> actionOnCard | C10: =#REF! -> #REF! | D10: =#REF! -> #REF! | E10: =LEFT(A10,1)&SUBSTITUTE(SUBSTITUTE(SUBSTITUTE(SUBSTITUTE(SUBSTITUTE(SUBSTITUTE(SUBSTITUTE(RIGHT(A10,LEN(A10)-1),"a"," "),"e"," "),"i"," "),"o"," "),"u"," "),"y"," ")," ","") -> crdCntxt | F10: =LEFT(B10,1)&SUBSTITUTE(SUBSTITUTE(SUBSTITUTE(SUBSTITUTE(SUBSTITUTE(SUBSTITUTE(SUBSTITUTE(RIGHT(B10,LEN(B10)-1),"a"," "),"e"," "),"i"," "),"o"," "),"u"," "),"y"," ")," ","") -> actnOnCrd | G10: =LEFT(C10,1)&SUBSTITUTE(SUBSTITUTE(SUBSTITUTE(SUBSTITUTE(SUBSTITUTE(SUBSTITUTE(SUBSTITUTE(RIGHT(C10,LEN(C10)-1),"a"," "),"e"," "),"i"," "),"o"," "),"u"," "),"y"," ")," ","") -> #REF! | H10: =LEFT(D10,1)&SUBSTITUTE(SUBSTITUTE(SUBSTITUTE(SUBSTITUTE(SUBSTITUTE(SUBSTITUTE(SUBSTITUTE(RIGHT(D10,LEN(D10)-1),"a"," "),"e"," "),"i"," "),"o"," "),"u"," "),"y"," ")," ","") -> #REF!
A11: =DICO_Export!D11 -> cardContext | B11: =DICO_Export!E11 -> activationCodeForNoShowInvoice | C11: =#REF! -> #REF! | D11: =#REF! -> #REF! | E11: =LEFT(A11,1)&SUBSTITUTE(SUBSTITUTE(SUBSTITUTE(SUBSTITUTE(SUBSTITUTE(SUBSTITUTE(SUBSTITUTE(RIGHT(A11,LEN(A11)-1),"a"," "),"e"," "),"i"," "),"o"," "),"u"," "),"y"," ")," ","") -> crdCntxt | F11: =LEFT(B11,1)&SUBSTITUTE(SUBSTITUTE(SUBSTITUTE(SUBSTITUTE(SUBSTITUTE(SUBSTITUTE(SUBSTITUTE(RIGHT(B11,LEN(B11)-1),"a"," "),"e"," "),"i"," "),"o"," "),"u"," "),"y"," ")," ","") -> actvtnCdFrNShwInvc | G11: =LEFT(C11,1)&SUBSTITUTE(SUBSTITUTE(SUBSTITUTE(SUBSTITUTE(SUBSTITUTE(SUBSTITUTE(SUBSTITUTE(RIGHT(C11,LEN(C11)-1),"a"," "),"e"," "),"i"," "),"o"," "),"u"," "),"y"," ")," ","") -> #REF! | H11: =LEFT(D11,1)&SUBSTITUTE(SUBSTITUTE(SUBSTITUTE(SUBSTITUTE(SUBSTITUTE(SUBSTITUTE(SUBSTITUTE(RIGHT(D11,LEN(D11)-1),"a"," "),"e"," "),"i"," "),"o"," "),"u"," "),"y"," ")," ","") -> #REF!
A12: =DICO_Export!D12 -> cardContext | B12: =DICO_Export!E12 -> activCodePLBSInvoiceRemoteModeOrPreAuthProlongTransaction | C12: =#REF! -> #REF! | D12: =#REF! -> #REF! | E12: =LEFT(A12,1)&SUBSTITUTE(SUBSTITUTE(SUBSTITUTE(SUBSTITUTE(SUBSTITUTE(SUBSTITUTE(SUBSTITUTE(RIGHT(A12,LEN(A12)-1),"a"," "),"e"," "),"i"," "),"o"," "),"u"," "),"y"," ")," ","") -> crdCntxt | F12: =LEFT(B12,1)&SUBSTITUTE(SUBSTITUTE(SUBSTITUTE(SUBSTITUTE(SUBSTITUTE(SUBSTITUTE(SUBSTITUTE(RIGHT(B12,LEN(B12)-1),"a"," "),"e"," "),"i"," "),"o"," "),"u"," "),"y"," ")," ","") -> actvCdPLBSInvcRmtMdOrPrAthPrlngTrnsctn | G12: =LEFT(C12,1)&SUBSTITUTE(SUBSTITUTE(SUBSTITUTE(SUBSTITUTE(SUBSTITUTE(SUBSTITUTE(SUBSTITUTE(RIGHT(C12,LEN(C12)-1),"a"," "),"e"," "),"i"," "),"o"," "),"u"," "),"y"," ")," ","") -> #REF! | H12: =LEFT(D12,1)&SUBSTITUTE(SUBSTITUTE(SUBSTITUTE(SUBSTITUTE(SUBSTITUTE(SUBSTITUTE(SUBSTITUTE(RIGHT(D12,LEN(D12)-1),"a"," "),"e"," "),"i"," "),"o"," "),"u"," "),"y"," ")," ","") -> #REF!
A13: =DICO_Export!D13 -> cardContext | B13: =DICO_Export!E13 -> additionalInvoiceActivationCode | C13: =#REF! -> #REF! | D13: =#REF! -> #REF! | E13: =LEFT(A13,1)&SUBSTITUTE(SUBSTITUTE(SUBSTITUTE(SUBSTITUTE(SUBSTITUTE(SUBSTITUTE(SUBSTITUTE(RIGHT(A13,LEN(A13)-1),"a"," "),"e"," "),"i"," "),"o"," "),"u"," "),"y"," ")," ","") -> crdCntxt | F13: =LEFT(B13,1)&SUBSTITUTE(SUBSTITUTE(SUBSTITUTE(SUBSTITUTE(SUBSTITUTE(SUBSTITUTE(SUBSTITUTE(RIGHT(B13,LEN(B13)-1),"a"," "),"e"," "),"i"," "),"o"," "),"u"," "),"y"," ")," ","") -> addtnlInvcActvtnCd | G13: =LEFT(C13,1)&SUBSTITUTE(SUBSTITUTE(SUBSTITUTE(SUBSTITUTE(SUBSTITUTE(SUBSTITUTE(SUBSTITUTE(RIGHT(C13,LEN(C13)-1),"a"," "),"e"," "),"i"," "),"o"," "),"u"," "),"y"," ")," ","") -> #REF! | H13: =LEFT(D13,1)&SUBSTITUTE(SUBSTITUTE(SUBSTITUTE(SUBSTITUTE(SUBSTITUTE(SUBSTITUTE(SUBSTITUTE(RIGHT(D13,LEN(D13)-1),"a"," "),"e"," "),"i"," "),"o"," "),"u"," "),"y"," ")," ","") -> #REF!
A14: =DICO_Export!D14 -> cardContext | B14: =DICO_Export!E14 -> blockingReasonCode | C14: =#REF! -> #REF! | D14: =#REF! -> #REF! | E14: =LEFT(A14,1)&SUBSTITUTE(SUBSTITUTE(SUBSTITUTE(SUBSTITUTE(SUBSTITUTE(SUBSTITUTE(SUBSTITUTE(RIGHT(A14,LEN(A14)-1),"a"," "),"e"," "),"i"," "),"o"," "),"u"," "),"y"," ")," ","") -> crdCntxt | F14: =LEFT(B14,1)&SUBSTITUTE(SUBSTITUTE(SUBSTITUTE(SUBSTITUTE(SUBSTITUTE(SUBSTITUTE(SUBSTITUTE(RIGHT(B14,LEN(B14)-1),"a"," "),"e"," "),"i"," "),"o"," "),"u"," "),"y"," ")," ","") -> blckngRsnCd | G14: =LEFT(C14,1)&SUBSTITUTE(SUBSTITUTE(SUBSTITUTE(SUBSTITUTE(SUBSTITUTE(SUBSTITUTE(SUBSTITUTE(RIGHT(C14,LEN(C14)-1),"a"," "),"e"," "),"i"," "),"o"," "),"u"," "),"y"," ")," ","") -> #REF! | H14: =LEFT(D14,1)&SUBSTITUTE(SUBSTITUTE(SUBSTITUTE(SUBSTITUTE(SUBSTITUTE(SUBSTITUTE(SUBSTITUTE(RIGHT(D14,LEN(D14)-1),"a"," "),"e"," "),"i"," "),"o"," "),"u"," "),"y"," ")," ","") -> #REF!
... A446: =DICO_Export!D446 -> merchant | B446: =DICO_Export!E446 -> singleContractIndicator | C446: =#REF! -> #REF! | D446: =#REF! -> #REF! | E446: =LEFT(A446,1)&SUBSTITUTE(SUBSTITUTE(SUBSTITUTE(SUBSTITUTE(SUBSTITUTE(SUBSTITUTE(SUBSTITUTE(RIGHT(A446,LEN(A446)-1),"a"," "),"e"," "),"i"," "),"o"," "),"u"," "),"y"," ")," ","") -> mrchnt | F446: =LEFT(B446,1)&SUBSTITUTE(SUBSTITUTE(SUBSTITUTE(SUBSTITUTE(SUBSTITUTE(SUBSTITUTE(SUBSTITUTE(RIGHT(B446,LEN(B446)-1),"a"," "),"e"," "),"i"," "),"o"," "),"u"," "),"y"," ")," ","") -> snglCntrctIndctr | G446: =LEFT(C446,1)&SUBSTITUTE(SUBSTITUTE(SUBSTITUTE(SUBSTITUTE(SUBSTITUTE(SUBSTITUTE(SUBSTITUTE(RIGHT(C446,LEN(C446)-1),"a"," "),"e"," "),"i"," "),"o"," "),"u"," "),"y"," ")," ","") -> #REF! | H446: =LEFT(D446,1)&SUBSTITUTE(SUBSTITUTE(SUBSTITUTE(SUBSTITUTE(SUBSTITUTE(SUBSTITUTE(SUBSTITUTE(RIGHT(D446,LEN(D446)-1),"a"," "),"e"," "),"i"," "),"o"," "),"u"," "),"y"," ")," ","") -> #REF!
A447: =DICO_Export!#REF! -> #REF! | B447: =DICO_Export!#REF! -> #REF! | C447: =#REF! -> #REF! | D447: =#REF! -> #REF! | E447: =LEFT(A447,1)&SUBSTITUTE(SUBSTITUTE(SUBSTITUTE(SUBSTITUTE(SUBSTITUTE(SUBSTITUTE(SUBSTITUTE(RIGHT(A447,LEN(A447)-1),"a"," "),"e"," "),"i"," "),"o"," "),"u"," "),"y"," ")," ","") -> #REF! | F447: =LEFT(B447,1)&SUBSTITUTE(SUBSTITUTE(SUBSTITUTE(SUBSTITUTE(SUBSTITUTE(SUBSTITUTE(SUBSTITUTE(RIGHT(B447,LEN(B447)-1),"a"," "),"e"," "),"i"," "),"o"," "),"u"," "),"y"," ")," ","") -> #REF! | G447: =LEFT(C447,1)&SUBSTITUTE(SUBSTITUTE(SUBSTITUTE(SUBSTITUTE(SUBSTITUTE(SUBSTITUTE(SUBSTITUTE(RIGHT(C447,LEN(C447)-1),"a"," "),"e"," "),"i"," "),"o"," "),"u"," "),"y"," ")," ","") -> #REF! | H447: =LEFT(D447,1)&SUBSTITUTE(SUBSTITUTE(SUBSTITUTE(SUBSTITUTE(SUBSTITUTE(SUBSTITUTE(SUBSTITUTE(RIGHT(D447,LEN(D447)-1),"a"," "),"e"," "),"i"," "),"o"," "),"u"," "),"y"," ")," ","") -> #REF!
A448: =DICO_Export!#REF! -> #REF! | B448: =DICO_Export!#REF! -> #REF! | C448: =#REF! -> #REF! | D448: =#REF! -> #REF! | E448: =LEFT(A448,1)&SUBSTITUTE(SUBSTITUTE(SUBSTITUTE(SUBSTITUTE(SUBSTITUTE(SUBSTITUTE(SUBSTITUTE(RIGHT(A448,LEN(A448)-1),"a"," "),"e"," "),"i"," "),"o"," "),"u"," "),"y"," ")," ","") -> #REF! | F448: =LEFT(B448,1)&SUBSTITUTE(SUBSTITUTE(SUBSTITUTE(SUBSTITUTE(SUBSTITUTE(SUBSTITUTE(SUBSTITUTE(RIGHT(B448,LEN(B448)-1),"a"," "),"e"," "),"i"," "),"o"," "),"u"," "),"y"," ")," ","") -> #REF! | G448: =LEFT(C448,1)&SUBSTITUTE(SUBSTITUTE(SUBSTITUTE(SUBSTITUTE(SUBSTITUTE(SUBSTITUTE(SUBSTITUTE(RIGHT(C448,LEN(C448)-1),"a"," "),"e"," "),"i"," "),"o"," "),"u"," "),"y"," ")," ","") -> #REF! | H448: =LEFT(D448,1)&SUBSTITUTE(SUBSTITUTE(SUBSTITUTE(SUBSTITUTE(SUBSTITUTE(SUBSTITUTE(SUBSTITUTE(RIGHT(D448,LEN(D448)-1),"a"," "),"e"," "),"i"," "),"o"," "),"u"," "),"y"," ")," ","") -> #REF!
A449: =DICO_Export!#REF! -> #REF! | B449: =DICO_Export!#REF! -> #REF! | C449: =#REF! -> #REF! | D449: =#REF! -> #REF! | E449: =LEFT(A449,1)&SUBSTITUTE(SUBSTITUTE(SUBSTITUTE(SUBSTITUTE(SUBSTITUTE(SUBSTITUTE(SUBSTITUTE(RIGHT(A449,LEN(A449)-1),"a"," "),"e"," "),"i"," "),"o"," "),"u"," "),"y"," ")," ","") -> #REF! | F449: =LEFT(B449,1)&SUBSTITUTE(SUBSTITUTE(SUBSTITUTE(SUBSTITUTE(SUBSTITUTE(SUBSTITUTE(SUBSTITUTE(RIGHT(B449,LEN(B449)-1),"a"," "),"e"," "),"i"," "),"o"," "),"u"," "),"y"," ")," ","") -> #REF! | G449: =LEFT(C449,1)&SUBSTITUTE(SUBSTITUTE(SUBSTITUTE(SUBSTITUTE(SUBSTITUTE(SUBSTITUTE(SUBSTITUTE(RIGHT(C449,LEN(C449)-1),"a"," "),"e"," "),"i"," "),"o"," "),"u"," "),"y"," ")," ","") -> #REF! | H449: =LEFT(D449,1)&SUBSTITUTE(SUBSTITUTE(SUBSTITUTE(SUBSTITUTE(SUBSTITUTE(SUBSTITUTE(SUBSTITUTE(RIGHT(D449,LEN(D449)-1),"a"," "),"e"," "),"i"," "),"o"," "),"u"," "),"y"," ")," ","") -> #REF!
A450: =DICO_Export!#REF! -> #REF! | B450: =DICO_Export!#REF! -> #REF! | C450: =#REF! -> #REF! | D450: =#REF! -> #REF! | E450: =LEFT(A450,1)&SUBSTITUTE(SUBSTITUTE(SUBSTITUTE(SUBSTITUTE(SUBSTITUTE(SUBSTITUTE(SUBSTITUTE(RIGHT(A450,LEN(A450)-1),"a"," "),"e"," "),"i"," "),"o"," "),"u"," "),"y"," ")," ","") -> #REF! | F450: =LEFT(B450,1)&SUBSTITUTE(SUBSTITUTE(SUBSTITUTE(SUBSTITUTE(SUBSTITUTE(SUBSTITUTE(SUBSTITUTE(RIGHT(B450,LEN(B450)-1),"a"," "),"e"," "),"i"," "),"o"," "),"u"," "),"y"," ")," ","") -> #REF! | G450: =LEFT(C450,1)&SUBSTITUTE(SUBSTITUTE(SUBSTITUTE(SUBSTITUTE(SUBSTITUTE(SUBSTITUTE(SUBSTITUTE(RIGHT(C450,LEN(C450)-1),"a"," "),"e"," "),"i"," "),"o"," "),"u"," "),"y"," ")," ","") -> #REF! | H450: =LEFT(D450,1)&SUBSTITUTE(SUBSTITUTE(SUBSTITUTE(SUBSTITUTE(SUBSTITUTE(SUBSTITUTE(SUBSTITUTE(RIGHT(D450,LEN(D450)-1),"a"," "),"e"," "),"i"," "),"o"," "),"u"," "),"y"," ")," ","") -> #REF!
A451: =DICO_Export!#REF! -> #REF! | B451: =DICO_Export!#REF! -> #REF! | C451: =#REF! -> #REF! | D451: =#REF! -> #REF! | E451: =LEFT(A451,1)&SUBSTITUTE(SUBSTITUTE(SUBSTITUTE(SUBSTITUTE(SUBSTITUTE(SUBSTITUTE(SUBSTITUTE(RIGHT(A451,LEN(A451)-1),"a"," "),"e"," "),"i"," "),"o"," "),"u"," "),"y"," ")," ","") -> #REF! | F451: =LEFT(B451,1)&SUBSTITUTE(SUBSTITUTE(SUBSTITUTE(SUBSTITUTE(SUBSTITUTE(SUBSTITUTE(SUBSTITUTE(RIGHT(B451,LEN(B451)-1),"a"," "),"e"," "),"i"," "),"o"," "),"u"," "),"y"," ")," ","") -> #REF! | G451: =LEFT(C451,1)&SUBSTITUTE(SUBSTITUTE(SUBSTITUTE(SUBSTITUTE(SUBSTITUTE(SUBSTITUTE(SUBSTITUTE(RIGHT(C451,LEN(C451)-1),"a"," "),"e"," "),"i"," "),"o"," "),"u"," "),"y"," ")," ","") -> #REF! | H451: =LEFT(D451,1)&SUBSTITUTE(SUBSTITUTE(SUBSTITUTE(SUBSTITUTE(SUBSTITUTE(SUBSTITUTE(SUBSTITUTE(RIGHT(D451,LEN(D451)-1),"a"," "),"e"," "),"i"," "),"o"," "),"u"," "),"y"," ")," ","") -> #REF!
A452: =DICO_Export!D447 -> merchant | B452: =DICO_Export!E447 -> temp_anonymousDynamicPlaque | C452: =#REF! -> #REF! | D452: =#REF! -> #REF! | E452: =LEFT(A452,1)&SUBSTITUTE(SUBSTITUTE(SUBSTITUTE(SUBSTITUTE(SUBSTITUTE(SUBSTITUTE(SUBSTITUTE(RIGHT(A452,LEN(A452)-1),"a"," "),"e"," "),"i"," "),"o"," "),"u"," "),"y"," ")," ","") -> mrchnt | F452: =LEFT(B452,1)&SUBSTITUTE(SUBSTITUTE(SUBSTITUTE(SUBSTITUTE(SUBSTITUTE(SUBSTITUTE(SUBSTITUTE(RIGHT(B452,LEN(B452)-1),"a"," "),"e"," "),"i"," "),"o"," "),"u"," "),"y"," ")," ","") -> tmp_nnmsDnmcPlq | G452: =LEFT(C452,1)&SUBSTITUTE(SUBSTITUTE(SUBSTITUTE(SUBSTITUTE(SUBSTITUTE(SUBSTITUTE(SUBSTITUTE(RIGHT(C452,LEN(C452)-1),"a"," "),"e"," "),"i"," "),"o"," "),"u"," "),"y"," ")," ","") -> #REF! | H452: =LEFT(D452,1)&SUBSTITUTE(SUBSTITUTE(SUBSTITUTE(SUBSTITUTE(SUBSTITUTE(SUBSTITUTE(SUBSTITUTE(RIGHT(D452,LEN(D452)-1),"a"," "),"e"," "),"i"," "),"o"," "),"u"," "),"y"," ")," ","") -> #REF!
A453: =DICO_Export!D448 -> merchant | B453: =DICO_Export!E448 -> temp_merchantCommunicationMedia | C453: =#REF! -> #REF! | D453: =#REF! -> #REF! | E453: =LEFT(A453,1)&SUBSTITUTE(SUBSTITUTE(SUBSTITUTE(SUBSTITUTE(SUBSTITUTE(SUBSTITUTE(SUBSTITUTE(RIGHT(A453,LEN(A453)-1),"a"," "),"e"," "),"i"," "),"o"," "),"u"," "),"y"," ")," ","") -> mrchnt | F453: =LEFT(B453,1)&SUBSTITUTE(SUBSTITUTE(SUBSTITUTE(SUBSTITUTE(SUBSTITUTE(SUBSTITUTE(SUBSTITUTE(RIGHT(B453,LEN(B453)-1),"a"," "),"e"," "),"i"," "),"o"," "),"u"," "),"y"," ")," ","") -> tmp_mrchntCmmnctnMd | G453: =LEFT(C453,1)&SUBSTITUTE(SUBSTITUTE(SUBSTITUTE(SUBSTITUTE(SUBSTITUTE(SUBSTITUTE(SUBSTITUTE(RIGHT(C453,LEN(C453)-1),"a"," "),"e"," "),"i"," "),"o"," "),"u"," "),"y"," ")," ","") -> #REF! | H453: =LEFT(D453,1)&SUBSTITUTE(SUBSTITUTE(SUBSTITUTE(SUBSTITUTE(SUBSTITUTE(SUBSTITUTE(SUBSTITUTE(RIGHT(D453,LEN(D453)-1),"a"," "),"e"," "),"i"," "),"o"," "),"u"," "),"y"," ")," ","") -> #REF!
A454: =DICO_Export!D450 -> merchant | B454: =DICO_Export!E450 -> temp_productIdMasterRepository | C454: =#REF! -> #REF! | D454: =#REF! -> #REF! | E454: =LEFT(A454,1)&SUBSTITUTE(SUBSTITUTE(SUBSTITUTE(SUBSTITUTE(SUBSTITUTE(SUBSTITUTE(SUBSTITUTE(RIGHT(A454,LEN(A454)-1),"a"," "),"e"," "),"i"," "),"o"," "),"u"," "),"y"," ")," ","") -> mrchnt | F454: =LEFT(B454,1)&SUBSTITUTE(SUBSTITUTE(SUBSTITUTE(SUBSTITUTE(SUBSTITUTE(SUBSTITUTE(SUBSTITUTE(RIGHT(B454,LEN(B454)-1),"a"," "),"e"," "),"i"," "),"o"," "),"u"," "),"y"," ")," ","") -> tmp_prdctIdMstrRpstr | G454: =LEFT(C454,1)&SUBSTITUTE(SUBSTITUTE(SUBSTITUTE(SUBSTITUTE(SUBSTITUTE(SUBSTITUTE(SUBSTITUTE(RIGHT(C454,LEN(C454)-1),"a"," "),"e"," "),"i"," "),"o"," "),"u"," "),"y"," ")," ","") -> #REF! | H454: =LEFT(D454,1)&SUBSTITUTE(SUBSTITUTE(SUBSTITUTE(SUBSTITUTE(SUBSTITUTE(SUBSTITUTE(SUBSTITUTE(RIGHT(D454,LEN(D454)-1),"a"," "),"e"," "),"i"," "),"o"," "),"u"," "),"y"," ")," ","") -> #REF!
A455: =DICO_Export!D451 -> merchant | B455: =DICO_Export!E451 -> temp_visaMarketPlaceId | C455: =#REF! -> #REF! | D455: =#REF! -> #REF! | E455: =LEFT(A455,1)&SUBSTITUTE(SUBSTITUTE(SUBSTITUTE(SUBSTITUTE(SUBSTITUTE(SUBSTITUTE(SUBSTITUTE(RIGHT(A455,LEN(A455)-1),"a"," "),"e"," "),"i"," "),"o"," "),"u"," "),"y"," ")," ","") -> mrchnt | F455: =LEFT(B455,1)&SUBSTITUTE(SUBSTITUTE(SUBSTITUTE(SUBSTITUTE(SUBSTITUTE(SUBSTITUTE(SUBSTITUTE(RIGHT(B455,LEN(B455)-1),"a"," "),"e"," "),"i"," "),"o"," "),"u"," "),"y"," ")," ","") -> tmp_vsMrktPlcId | G455: =LEFT(C455,1)&SUBSTITUTE(SUBSTITUTE(SUBSTITUTE(SUBSTITUTE(SUBSTITUTE(SUBSTITUTE(SUBSTITUTE(RIGHT(C455,LEN(C455)-1),"a"," "),"e"," "),"i"," "),"o"," "),"u"," "),"y"," ")," ","") -> #REF! | H455: =LEFT(D455,1)&SUBSTITUTE(SUBSTITUTE(SUBSTITUTE(SUBSTITUTE(SUBSTITUTE(SUBSTITUTE(SUBSTITUTE(RIGHT(D455,LEN(D455)-1),"a"," "),"e"," "),"i"," "),"o"," "),"u"," "),"y"," ")," ","") -> #REF!
A456: =DICO_Export!D452 -> payee | B456: =DICO_Export!E452 -> accountNumber | C456: =#REF! -> #REF! | D456: =#REF! -> #REF! | E456: =LEFT(A456,1)&SUBSTITUTE(SUBSTITUTE(SUBSTITUTE(SUBSTITUTE(SUBSTITUTE(SUBSTITUTE(SUBSTITUTE(RIGHT(A456,LEN(A456)-1),"a"," "),"e"," "),"i"," "),"o"," "),"u"," "),"y"," ")," ","") -> p | F456: =LEFT(B456,1)&SUBSTITUTE(SUBSTITUTE(SUBSTITUTE(SUBSTITUTE(SUBSTITUTE(SUBSTITUTE(SUBSTITUTE(RIGHT(B456,LEN(B456)-1),"a"," "),"e"," "),"i"," "),"o"," "),"u"," "),"y"," ")," ","") -> accntNmbr | G456: =LEFT(C456,1)&SUBSTITUTE(SUBSTITUTE(SUBSTITUTE(SUBSTITUTE(SUBSTITUTE(SUBSTITUTE(SUBSTITUTE(RIGHT(C456,LEN(C456)-1),"a"," "),"e"," "),"i"," "),"o"," "),"u"," "),"y"," ")," ","") -> #REF! | H456: =LEFT(D456,1)&SUBSTITUTE(SUBSTITUTE(SUBSTITUTE(SUBSTITUTE(SUBSTITUTE(SUBSTITUTE(SUBSTITUTE(RIGHT(D456,LEN(D456)-1),"a"," "),"e"," "),"i"," "),"o"," "),"u"," "),"y"," ")," ","") -> #REF!
A457: =DICO_Export!D453 -> payee | B457: =DICO_Export!E453 -> primaryAccountNumber | C457: =#REF! -> #REF! | D457: =#REF! -> #REF! | E457: =LEFT(A457,1)&SUBSTITUTE(SUBSTITUTE(SUBSTITUTE(SUBSTITUTE(SUBSTITUTE(SUBSTITUTE(SUBSTITUTE(RIGHT(A457,LEN(A457)-1),"a"," "),"e"," "),"i"," "),"o"," "),"u"," "),"y"," ")," ","") -> p | F457: =LEFT(B457,1)&SUBSTITUTE(SUBSTITUTE(SUBSTITUTE(SUBSTITUTE(SUBSTITUTE(SUBSTITUTE(SUBSTITUTE(RIGHT(B457,LEN(B457)-1),"a"," "),"e"," "),"i"," "),"o"," "),"u"," "),"y"," ")," ","") -> prmrAccntNmbr | G457: =LEFT(C457,1)&SUBSTITUTE(SUBSTITUTE(SUBSTITUTE(SUBSTITUTE(SUBSTITUTE(SUBSTITUTE(SUBSTITUTE(RIGHT(C457,LEN(C457)-1),"a"," "),"e"," "),"i"," "),"o"," "),"u"," "),"y"," ")," ","") -> #REF! | H457: =LEFT(D457,1)&SUBSTITUTE(SUBSTITUTE(SUBSTITUTE(SUBSTITUTE(SUBSTITUTE(SUBSTITUTE(SUBSTITUTE(RIGHT(D457,LEN(D457)-1),"a"," "),"e"," "),"i"," "),"o"," "),"u"," "),"y"," ")," ","") -> #REF!
A458: =DICO_Export!D454 -> payer | B458: =DICO_Export!E454 -> accountNumber | C458: =#REF! -> #REF! | D458: =#REF! -> #REF! | E458: =LEFT(A458,1)&SUBSTITUTE(SUBSTITUTE(SUBSTITUTE(SUBSTITUTE(SUBSTITUTE(SUBSTITUTE(SUBSTITUTE(RIGHT(A458,LEN(A458)-1),"a"," "),"e"," "),"i"," "),"o"," "),"u"," "),"y"," ")," ","") -> pr | F458: =LEFT(B458,1)&SUBSTITUTE(SUBSTITUTE(SUBSTITUTE(SUBSTITUTE(SUBSTITUTE(SUBSTITUTE(SUBSTITUTE(RIGHT(B458,LEN(B458)-1),"a"," "),"e"," "),"i"," "),"o"," "),"u"," "),"y"," ")," ","") -> accntNmbr | G458: =LEFT(C458,1)&SUBSTITUTE(SUBSTITUTE(SUBSTITUTE(SUBSTITUTE(SUBSTITUTE(SUBSTITUTE(SUBSTITUTE(RIGHT(C458,LEN(C458)-1),"a"," "),"e"," "),"i"," "),"o"," "),"u"," "),"y"," ")," ","") -> #REF! | H458: =LEFT(D458,1)&SUBSTITUTE(SUBSTITUTE(SUBSTITUTE(SUBSTITUTE(SUBSTITUTE(SUBSTITUTE(SUBSTITUTE(RIGHT(D458,LEN(D458)-1),"a"," "),"e"," "),"i"," "),"o"," "),"u"," "),"y"," ")," ","") -> #REF!
A459: =DICO_Export!D455 -> payer | B459: =DICO_Export!E455 -> financialInstitutionId | C459: =#REF! -> #REF! | D459: =#REF! -> #REF! | E459: =LEFT(A459,1)&SUBSTITUTE(SUBSTITUTE(SUBSTITUTE(SUBSTITUTE(SUBSTITUTE(SUBSTITUTE(SUBSTITUTE(RIGHT(A459,LEN(A459)-1),"a"," "),"e"," "),"i"," "),"o"," "),"u"," "),"y"," ")," ","") -> pr | F459: =LEFT(B459,1)&SUBSTITUTE(SUBSTITUTE(SUBSTITUTE(SUBSTITUTE(SUBSTITUTE(SUBSTITUTE(SUBSTITUTE(RIGHT(B459,LEN(B459)-1),"a"," "),"e"," "),"i"," "),"o"," "),"u"," "),"y"," ")," ","") -> fnnclInstttnId | G459: =LEFT(C459,1)&SUBSTITUTE(SUBSTITUTE(SUBSTITUTE(SUBSTITUTE(SUBSTITUTE(SUBSTITUTE(SUBSTITUTE(RIGHT(C459,LEN(C459)-1),"a"," "),"e"," "),"i"," "),"o"," "),"u"," "),"y"," ")," ","") -> #REF! | H459: =LEFT(D459,1)&SUBSTITUTE(SUBSTITUTE(SUBSTITUTE(SUBSTITUTE(SUBSTITUTE(SUBSTITUTE(SUBSTITUTE(RIGHT(D459,LEN(D459)-1),"a"," "),"e"," "),"i"," "),"o"," "),"u"," "),"y"," ")," ","") -> #REF!
A460: =DICO_Export!D456 -> payer | B460: =DICO_Export!E456 -> internationalBankAccountNumber | C460: =#REF! -> #REF! | D460: =#REF! -> #REF! | E460: =LEFT(A460,1)&SUBSTITUTE(SUBSTITUTE(SUBSTITUTE(SUBSTITUTE(SUBSTITUTE(SUBSTITUTE(SUBSTITUTE(RIGHT(A460,LEN(A460)-1),"a"," "),"e"," "),"i"," "),"o"," "),"u"," "),"y"," ")," ","") -> pr | F460: =LEFT(B460,1)&SUBSTITUTE(SUBSTITUTE(SUBSTITUTE(SUBSTITUTE(SUBSTITUTE(SUBSTITUTE(SUBSTITUTE(RIGHT(B460,LEN(B460)-1),"a"," "),"e"," "),"i"," "),"o"," "),"u"," "),"y"," ")," ","") -> intrntnlBnkAccntNmbr | G460: =LEFT(C460,1)&SUBSTITUTE(SUBSTITUTE(SUBSTITUTE(SUBSTITUTE(SUBSTITUTE(SUBSTITUTE(SUBSTITUTE(RIGHT(C460,LEN(C460)-1),"a"," "),"e"," "),"i"," "),"o"," "),"u"," "),"y"," ")," ","") -> #REF! | H460: =LEFT(D460,1)&SUBSTITUTE(SUBSTITUTE(SUBSTITUTE(SUBSTITUTE(SUBSTITUTE(SUBSTITUTE(SUBSTITUTE(RIGHT(D460,LEN(D460)-1),"a"," "),"e"," "),"i"," "),"o"," "),"u"," "),"y"," ")," ","") -> #REF!
A461: =DICO_Export!D457 -> sponsoredMerchant | B461: =DICO_Export!E457 -> finalMerchantAdress | C461: =#REF! -> #REF! | D461: =#REF! -> #REF! | E461: =LEFT(A461,1)&SUBSTITUTE(SUBSTITUTE(SUBSTITUTE(SUBSTITUTE(SUBSTITUTE(SUBSTITUTE(SUBSTITUTE(RIGHT(A461,LEN(A461)-1),"a"," "),"e"," "),"i"," "),"o"," "),"u"," "),"y"," ")," ","") -> spnsrdMrchnt | F461: =LEFT(B461,1)&SUBSTITUTE(SUBSTITUTE(SUBSTITUTE(SUBSTITUTE(SUBSTITUTE(SUBSTITUTE(SUBSTITUTE(RIGHT(B461,LEN(B461)-1),"a"," "),"e"," "),"i"," "),"o"," "),"u"," "),"y"," ")," ","") -> fnlMrchntAdrss | G461: =LEFT(C461,1)&SUBSTITUTE(SUBSTITUTE(SUBSTITUTE(SUBSTITUTE(SUBSTITUTE(SUBSTITUTE(SUBSTITUTE(RIGHT(C461,LEN(C461)-1),"a"," "),"e"," "),"i"," "),"o"," "),"u"," "),"y"," ")," ","") -> #REF! | H461: =LEFT(D461,1)&SUBSTITUTE(SUBSTITUTE(SUBSTITUTE(SUBSTITUTE(SUBSTITUTE(SUBSTITUTE(SUBSTITUTE(RIGHT(D461,LEN(D461)-1),"a"," "),"e"," "),"i"," "),"o"," "),"u"," "),"y"," ")," ","") -> #REF!
A462: =DICO_Export!D458 -> sponsoredMerchant | B462: =DICO_Export!E458 -> finalMerchantId | C462: =#REF! -> #REF! | D462: =#REF! -> #REF! | E462: =LEFT(A462,1)&SUBSTITUTE(SUBSTITUTE(SUBSTITUTE(SUBSTITUTE(SUBSTITUTE(SUBSTITUTE(SUBSTITUTE(RIGHT(A462,LEN(A462)-1),"a"," "),"e"," "),"i"," "),"o"," "),"u"," "),"y"," ")," ","") -> spnsrdMrchnt | F462: =LEFT(B462,1)&SUBSTITUTE(SUBSTITUTE(SUBSTITUTE(SUBSTITUTE(SUBSTITUTE(SUBSTITUTE(SUBSTITUTE(RIGHT(B462,LEN(B462)-1),"a"," "),"e"," "),"i"," "),"o"," "),"u"," "),"y"," ")," ","") -> fnlMrchntId | G462: =LEFT(C462,1)&SUBSTITUTE(SUBSTITUTE(SUBSTITUTE(SUBSTITUTE(SUBSTITUTE(SUBSTITUTE(SUBSTITUTE(RIGHT(C462,LEN(C462)-1),"a"," "),"e"," "),"i"," "),"o"," "),"u"," "),"y"," ")," ","") -> #REF! | H462: =LEFT(D462,1)&SUBSTITUTE(SUBSTITUTE(SUBSTITUTE(SUBSTITUTE(SUBSTITUTE(SUBSTITUTE(SUBSTITUTE(RIGHT(D462,LEN(D462)-1),"a"," "),"e"," "),"i"," "),"o"," "),"u"," "),"y"," ")," ","") -> #REF!
A463: =DICO_Export!D459 -> sponsoredMerchant | B463: =DICO_Export!E459 -> independantSalesOrganisationId | C463: =#REF! -> #REF! | D463: =#REF! -> #REF! | E463: =LEFT(A463,1)&SUBSTITUTE(SUBSTITUTE(SUBSTITUTE(SUBSTITUTE(SUBSTITUTE(SUBSTITUTE(SUBSTITUTE(RIGHT(A463,LEN(A463)-1),"a"," "),"e"," "),"i"," "),"o"," "),"u"," "),"y"," ")," ","") -> spnsrdMrchnt | F463: =LEFT(B463,1)&SUBSTITUTE(SUBSTITUTE(SUBSTITUTE(SUBSTITUTE(SUBSTITUTE(SUBSTITUTE(SUBSTITUTE(RIGHT(B463,LEN(B463)-1),"a"," "),"e"," "),"i"," "),"o"," "),"u"," "),"y"," ")," ","") -> indpndntSlsOrgnstnId | G463: =LEFT(C463,1)&SUBSTITUTE(SUBSTITUTE(SUBSTITUTE(SUBSTITUTE(SUBSTITUTE(SUBSTITUTE(SUBSTITUTE(RIGHT(C463,LEN(C463)-1),"a"," "),"e"," "),"i"," "),"o"," "),"u"," "),"y"," ")," ","") -> #REF! | H463: =LEFT(D463,1)&SUBSTITUTE(SUBSTITUTE(SUBSTITUTE(SUBSTITUTE(SUBSTITUTE(SUBSTITUTE(SUBSTITUTE(RIGHT(D463,LEN(D463)-1),"a"," "),"e"," "),"i"," "),"o"," "),"u"," "),"y"," ")," ","") -> #REF!
A464: =DICO_Export!D460 -> sponsoredMerchant | B464: =DICO_Export!E460 -> marketPlaceForeignRetailIndicator | C464: =#REF! -> #REF! | D464: =#REF! -> #REF! | E464: =LEFT(A464,1)&SUBSTITUTE(SUBSTITUTE(SUBSTITUTE(SUBSTITUTE(SUBSTITUTE(SUBSTITUTE(SUBSTITUTE(RIGHT(A464,LEN(A464)-1),"a"," "),"e"," "),"i"," "),"o"," "),"u"," "),"y"," ")," ","") -> spnsrdMrchnt | F464: =LEFT(B464,1)&SUBSTITUTE(SUBSTITUTE(SUBSTITUTE(SUBSTITUTE(SUBSTITUTE(SUBSTITUTE(SUBSTITUTE(RIGHT(B464,LEN(B464)-1),"a"," "),"e"," "),"i"," "),"o"," "),"u"," "),"y"," ")," ","") -> mrktPlcFrgnRtlIndctr | G464: =LEFT(C464,1)&SUBSTITUTE(SUBSTITUTE(SUBSTITUTE(SUBSTITUTE(SUBSTITUTE(SUBSTITUTE(SUBSTITUTE(RIGHT(C464,LEN(C464)-1),"a"," "),"e"," "),"i"," "),"o"," "),"u"," "),"y"," ")," ","") -> #REF! | H464: =LEFT(D464,1)&SUBSTITUTE(SUBSTITUTE(SUBSTITUTE(SUBSTITUTE(SUBSTITUTE(SUBSTITUTE(SUBSTITUTE(RIGHT(D464,LEN(D464)-1),"a"," "),"e"," "),"i"," "),"o"," "),"u"," "),"y"," ")," ","") -> #REF!
A465: =DICO_Export!D461 -> sponsoredMerchant | B465: =DICO_Export!E461 -> marketPlaceId | C465: =#REF! -> #REF! | D465: =#REF! -> #REF! | E465: =LEFT(A465,1)&SUBSTITUTE(SUBSTITUTE(SUBSTITUTE(SUBSTITUTE(SUBSTITUTE(SUBSTITUTE(SUBSTITUTE(RIGHT(A465,LEN(A465)-1),"a"," "),"e"," "),"i"," "),"o"," "),"u"," "),"y"," ")," ","") -> spnsrdMrchnt | F465: =LEFT(B465,1)&SUBSTITUTE(SUBSTITUTE(SUBSTITUTE(SUBSTITUTE(SUBSTITUTE(SUBSTITUTE(SUBSTITUTE(RIGHT(B465,LEN(B465)-1),"a"," "),"e"," "),"i"," "),"o"," "),"u"," "),"y"," ")," ","") -> mrktPlcId | G465: =LEFT(C465,1)&SUBSTITUTE(SUBSTITUTE(SUBSTITUTE(SUBSTITUTE(SUBSTITUTE(SUBSTITUTE(SUBSTITUTE(RIGHT(C465,LEN(C465)-1),"a"," "),"e"," "),"i"," "),"o"," "),"u"," "),"y"," ")," ","") -> #REF! | H465: =LEFT(D465,1)&SUBSTITUTE(SUBSTITUTE(SUBSTITUTE(SUBSTITUTE(SUBSTITUTE(SUBSTITUTE(SUBSTITUTE(RIGHT(D465,LEN(D465)-1),"a"," "),"e"," "),"i"," "),"o"," "),"u"," "),"y"," ")," ","") -> #REF!
... A731: =DICO_Export!D727 -> security | B731: =DICO_Export!E727 -> signatureAlgorithm | C731: =#REF! -> #REF! | D731: =#REF! -> #REF! | E731: =LEFT(A731,1)&SUBSTITUTE(SUBSTITUTE(SUBSTITUTE(SUBSTITUTE(SUBSTITUTE(SUBSTITUTE(SUBSTITUTE(RIGHT(A731,LEN(A731)-1),"a"," "),"e"," "),"i"," "),"o"," "),"u"," "),"y"," ")," ","") -> scrt | F731: =LEFT(B731,1)&SUBSTITUTE(SUBSTITUTE(SUBSTITUTE(SUBSTITUTE(SUBSTITUTE(SUBSTITUTE(SUBSTITUTE(RIGHT(B731,LEN(B731)-1),"a"," "),"e"," "),"i"," "),"o"," "),"u"," "),"y"," ")," ","") -> sgntrAlgrthm | G731: =LEFT(C731,1)&SUBSTITUTE(SUBSTITUTE(SUBSTITUTE(SUBSTITUTE(SUBSTITUTE(SUBSTITUTE(SUBSTITUTE(RIGHT(C731,LEN(C731)-1),"a"," "),"e"," "),"i"," "),"o"," "),"u"," "),"y"," ")," ","") -> #REF! | H731: =LEFT(D731,1)&SUBSTITUTE(SUBSTITUTE(SUBSTITUTE(SUBSTITUTE(SUBSTITUTE(SUBSTITUTE(SUBSTITUTE(RIGHT(D731,LEN(D731)-1),"a"," "),"e"," "),"i"," "),"o"," "),"u"," "),"y"," ")," ","") -> #REF!
G732: =LEFT(C732,1)&SUBSTITUTE(SUBSTITUTE(SUBSTITUTE(SUBSTITUTE(SUBSTITUTE(SUBSTITUTE(SUBSTITUTE(RIGHT(C732,LEN(C732)-1),"a"," "),"e"," "),"i"," "),"o"," "),"u"," "),"y"," ")," ","") -> #VALUE! | H732: =LEFT(D732,1)&SUBSTITUTE(SUBSTITUTE(SUBSTITUTE(SUBSTITUTE(SUBSTITUTE(SUBSTITUTE(SUBSTITUTE(RIGHT(D732,LEN(D732)-1),"a"," "),"e"," "),"i"," "),"o"," "),"u"," "),"y"," ")," ","") -> #VALUE!
G733: =LEFT(C733,1)&SUBSTITUTE(SUBSTITUTE(SUBSTITUTE(SUBSTITUTE(SUBSTITUTE(SUBSTITUTE(SUBSTITUTE(RIGHT(C733,LEN(C733)-1),"a"," "),"e"," "),"i"," "),"o"," "),"u"," "),"y"," ")," ","") -> #VALUE! | H733: =LEFT(D733,1)&SUBSTITUTE(SUBSTITUTE(SUBSTITUTE(SUBSTITUTE(SUBSTITUTE(SUBSTITUTE(SUBSTITUTE(RIGHT(D733,LEN(D733)-1),"a"," "),"e"," "),"i"," "),"o"," "),"u"," "),"y"," ")," ","") -> #VALUE!
G734: =LEFT(C734,1)&SUBSTITUTE(SUBSTITUTE(SUBSTITUTE(SUBSTITUTE(SUBSTITUTE(SUBSTITUTE(SUBSTITUTE(RIGHT(C734,LEN(C734)-1),"a"," "),"e"," "),"i"," "),"o"," "),"u"," "),"y"," ")," ","") -> #VALUE! | H734: =LEFT(D734,1)&SUBSTITUTE(SUBSTITUTE(SUBSTITUTE(SUBSTITUTE(SUBSTITUTE(SUBSTITUTE(SUBSTITUTE(RIGHT(D734,LEN(D734)-1),"a"," "),"e"," "),"i"," "),"o"," "),"u"," "),"y"," ")," ","") -> #VALUE!
G735: =LEFT(C735,1)&SUBSTITUTE(SUBSTITUTE(SUBSTITUTE(SUBSTITUTE(SUBSTITUTE(SUBSTITUTE(SUBSTITUTE(RIGHT(C735,LEN(C735)-1),"a"," "),"e"," "),"i"," "),"o"," "),"u"," "),"y"," ")," ","") -> #VALUE! | H735: =LEFT(D735,1)&SUBSTITUTE(SUBSTITUTE(SUBSTITUTE(SUBSTITUTE(SUBSTITUTE(SUBSTITUTE(SUBSTITUTE(RIGHT(D735,LEN(D735)-1),"a"," "),"e"," "),"i"," "),"o"," "),"u"," "),"y"," ")," ","") -> #VALUE!
G736: =LEFT(C736,1)&SUBSTITUTE(SUBSTITUTE(SUBSTITUTE(SUBSTITUTE(SUBSTITUTE(SUBSTITUTE(SUBSTITUTE(RIGHT(C736,LEN(C736)-1),"a"," "),"e"," "),"i"," "),"o"," "),"u"," "),"y"," ")," ","") -> #VALUE! | H736: =LEFT(D736,1)&SUBSTITUTE(SUBSTITUTE(SUBSTITUTE(SUBSTITUTE(SUBSTITUTE(SUBSTITUTE(SUBSTITUTE(RIGHT(D736,LEN(D736)-1),"a"," "),"e"," "),"i"," "),"o"," "),"u"," "),"y"," ")," ","") -> #VALUE!
G737: =LEFT(C737,1)&SUBSTITUTE(SUBSTITUTE(SUBSTITUTE(SUBSTITUTE(SUBSTITUTE(SUBSTITUTE(SUBSTITUTE(RIGHT(C737,LEN(C737)-1),"a"," "),"e"," "),"i"," "),"o"," "),"u"," "),"y"," ")," ","") -> #VALUE! | H737: =LEFT(D737,1)&SUBSTITUTE(SUBSTITUTE(SUBSTITUTE(SUBSTITUTE(SUBSTITUTE(SUBSTITUTE(SUBSTITUTE(RIGHT(D737,LEN(D737)-1),"a"," "),"e"," "),"i"," "),"o"," "),"u"," "),"y"," ")," ","") -> #VALUE!
G738: =LEFT(C738,1)&SUBSTITUTE(SUBSTITUTE(SUBSTITUTE(SUBSTITUTE(SUBSTITUTE(SUBSTITUTE(SUBSTITUTE(RIGHT(C738,LEN(C738)-1),"a"," "),"e"," "),"i"," "),"o"," "),"u"," "),"y"," ")," ","") -> #VALUE! | H738: =LEFT(D738,1)&SUBSTITUTE(SUBSTITUTE(SUBSTITUTE(SUBSTITUTE(SUBSTITUTE(SUBSTITUTE(SUBSTITUTE(RIGHT(D738,LEN(D738)-1),"a"," "),"e"," "),"i"," "),"o"," "),"u"," "),"y"," ")," ","") -> #VALUE!
G739: =LEFT(C739,1)&SUBSTITUTE(SUBSTITUTE(SUBSTITUTE(SUBSTITUTE(SUBSTITUTE(SUBSTITUTE(SUBSTITUTE(RIGHT(C739,LEN(C739)-1),"a"," "),"e"," "),"i"," "),"o"," "),"u"," "),"y"," ")," ","") -> #VALUE! | H739: =LEFT(D739,1)&SUBSTITUTE(SUBSTITUTE(SUBSTITUTE(SUBSTITUTE(SUBSTITUTE(SUBSTITUTE(SUBSTITUTE(RIGHT(D739,LEN(D739)-1),"a"," "),"e"," "),"i"," "),"o"," "),"u"," "),"y"," ")," ","") -> #VALUE!
G740: =LEFT(C740,1)&SUBSTITUTE(SUBSTITUTE(SUBSTITUTE(SUBSTITUTE(SUBSTITUTE(SUBSTITUTE(SUBSTITUTE(RIGHT(C740,LEN(C740)-1),"a"," "),"e"," "),"i"," "),"o"," "),"u"," "),"y"," ")," ","") -> #VALUE! | H740: =LEFT(D740,1)&SUBSTITUTE(SUBSTITUTE(SUBSTITUTE(SUBSTITUTE(SUBSTITUTE(SUBSTITUTE(SUBSTITUTE(RIGHT(D740,LEN(D740)-1),"a"," "),"e"," "),"i"," "),"o"," "),"u"," "),"y"," ")," ","") -> #VALUE!
G741: =LEFT(C741,1)&SUBSTITUTE(SUBSTITUTE(SUBSTITUTE(SUBSTITUTE(SUBSTITUTE(SUBSTITUTE(SUBSTITUTE(RIGHT(C741,LEN(C741)-1),"a"," "),"e"," "),"i"," "),"o"," "),"u"," "),"y"," ")," ","") -> #VALUE! | H741: =LEFT(D741,1)&SUBSTITUTE(SUBSTITUTE(SUBSTITUTE(SUBSTITUTE(SUBSTITUTE(SUBSTITUTE(SUBSTITUTE(RIGHT(D741,LEN(D741)-1),"a"," "),"e"," "),"i"," "),"o"," "),"u"," "),"y"," ")," ","") -> #VALUE!
G742: =LEFT(C742,1)&SUBSTITUTE(SUBSTITUTE(SUBSTITUTE(SUBSTITUTE(SUBSTITUTE(SUBSTITUTE(SUBSTITUTE(RIGHT(C742,LEN(C742)-1),"a"," "),"e"," "),"i"," "),"o"," "),"u"," "),"y"," ")," ","") -> #VALUE! | H742: =LEFT(D742,1)&SUBSTITUTE(SUBSTITUTE(SUBSTITUTE(SUBSTITUTE(SUBSTITUTE(SUBSTITUTE(SUBSTITUTE(RIGHT(D742,LEN(D742)-1),"a"," "),"e"," "),"i"," "),"o"," "),"u"," "),"y"," ")," ","") -> #VALUE!
G743: =LEFT(C743,1)&SUBSTITUTE(SUBSTITUTE(SUBSTITUTE(SUBSTITUTE(SUBSTITUTE(SUBSTITUTE(SUBSTITUTE(RIGHT(C743,LEN(C743)-1),"a"," "),"e"," "),"i"," "),"o"," "),"u"," "),"y"," ")," ","") -> #VALUE! | H743: =LEFT(D743,1)&SUBSTITUTE(SUBSTITUTE(SUBSTITUTE(SUBSTITUTE(SUBSTITUTE(SUBSTITUTE(SUBSTITUTE(RIGHT(D743,LEN(D743)-1),"a"," "),"e"," "),"i"," "),"o"," "),"u"," "),"y"," ")," ","") -> #VALUE!
... G751: =LEFT(C751,1)&SUBSTITUTE(SUBSTITUTE(SUBSTITUTE(SUBSTITUTE(SUBSTITUTE(SUBSTITUTE(SUBSTITUTE(RIGHT(C751,LEN(C751)-1),"a"," "),"e"," "),"i"," "),"o"," "),"u"," "),"y"," ")," ","") -> #VALUE! | H751: =LEFT(D751,1)&SUBSTITUTE(SUBSTITUTE(SUBSTITUTE(SUBSTITUTE(SUBSTITUTE(SUBSTITUTE(SUBSTITUTE(RIGHT(D751,LEN(D751)-1),"a"," "),"e"," "),"i"," "),"o"," "),"u"," "),"y"," ")," ","") -> #VALUE!
C752: =#REF! -> #REF! | D752: =#REF! -> #REF! | G752: =LEFT(C752,1)&SUBSTITUTE(SUBSTITUTE(SUBSTITUTE(SUBSTITUTE(SUBSTITUTE(SUBSTITUTE(SUBSTITUTE(RIGHT(C752,LEN(C752)-1),"a"," "),"e"," "),"i"," "),"o"," "),"u"," "),"y"," ")," ","") -> #REF! | H752: =LEFT(D752,1)&SUBSTITUTE(SUBSTITUTE(SUBSTITUTE(SUBSTITUTE(SUBSTITUTE(SUBSTITUTE(SUBSTITUTE(RIGHT(D752,LEN(D752)-1),"a"," "),"e"," "),"i"," "),"o"," "),"u"," "),"y"," ")," ","") -> #REF!
C753: =#REF! -> #REF! | D753: =#REF! -> #REF! | G753: =LEFT(C753,1)&SUBSTITUTE(SUBSTITUTE(SUBSTITUTE(SUBSTITUTE(SUBSTITUTE(SUBSTITUTE(SUBSTITUTE(RIGHT(C753,LEN(C753)-1),"a"," "),"e"," "),"i"," "),"o"," "),"u"," "),"y"," ")," ","") -> #REF! | H753: =LEFT(D753,1)&SUBSTITUTE(SUBSTITUTE(SUBSTITUTE(SUBSTITUTE(SUBSTITUTE(SUBSTITUTE(SUBSTITUTE(RIGHT(D753,LEN(D753)-1),"a"," "),"e"," "),"i"," "),"o"," "),"u"," "),"y"," ")," ","") -> #REF!
C754: =#REF! -> #REF! | D754: =#REF! -> #REF! | G754: =LEFT(C754,1)&SUBSTITUTE(SUBSTITUTE(SUBSTITUTE(SUBSTITUTE(SUBSTITUTE(SUBSTITUTE(SUBSTITUTE(RIGHT(C754,LEN(C754)-1),"a"," "),"e"," "),"i"," "),"o"," "),"u"," "),"y"," ")," ","") -> #REF! | H754: =LEFT(D754,1)&SUBSTITUTE(SUBSTITUTE(SUBSTITUTE(SUBSTITUTE(SUBSTITUTE(SUBSTITUTE(SUBSTITUTE(RIGHT(D754,LEN(D754)-1),"a"," "),"e"," "),"i"," "),"o"," "),"u"," "),"y"," ")," ","") -> #REF!
C755: =#REF! -> #REF! | D755: =#REF! -> #REF! | G755: =LEFT(C755,1)&SUBSTITUTE(SUBSTITUTE(SUBSTITUTE(SUBSTITUTE(SUBSTITUTE(SUBSTITUTE(SUBSTITUTE(RIGHT(C755,LEN(C755)-1),"a"," "),"e"," "),"i"," "),"o"," "),"u"," "),"y"," ")," ","") -> #REF! | H755: =LEFT(D755,1)&SUBSTITUTE(SUBSTITUTE(SUBSTITUTE(SUBSTITUTE(SUBSTITUTE(SUBSTITUTE(SUBSTITUTE(RIGHT(D755,LEN(D755)-1),"a"," "),"e"," "),"i"," "),"o"," "),"u"," "),"y"," ")," ","") -> #REF!
C756: =#REF! -> #REF! | D756: =#REF! -> #REF! | G756: =LEFT(C756,1)&SUBSTITUTE(SUBSTITUTE(SUBSTITUTE(SUBSTITUTE(SUBSTITUTE(SUBSTITUTE(SUBSTITUTE(RIGHT(C756,LEN(C756)-1),"a"," "),"e"," "),"i"," "),"o"," "),"u"," "),"y"," ")," ","") -> #REF! | H756: =LEFT(D756,1)&SUBSTITUTE(SUBSTITUTE(SUBSTITUTE(SUBSTITUTE(SUBSTITUTE(SUBSTITUTE(SUBSTITUTE(RIGHT(D756,LEN(D756)-1),"a"," "),"e"," "),"i"," "),"o"," "),"u"," "),"y"," ")," ","") -> #REF!
C757: =#REF! -> #REF! | D757: =#REF! -> #REF! | G757: =LEFT(C757,1)&SUBSTITUTE(SUBSTITUTE(SUBSTITUTE(SUBSTITUTE(SUBSTITUTE(SUBSTITUTE(SUBSTITUTE(RIGHT(C757,LEN(C757)-1),"a"," "),"e"," "),"i"," "),"o"," "),"u"," "),"y"," ")," ","") -> #REF! | H757: =LEFT(D757,1)&SUBSTITUTE(SUBSTITUTE(SUBSTITUTE(SUBSTITUTE(SUBSTITUTE(SUBSTITUTE(SUBSTITUTE(RIGHT(D757,LEN(D757)-1),"a"," "),"e"," "),"i"," "),"o"," "),"u"," "),"y"," ")," ","") -> #REF!
C758: =#REF! -> #REF! | D758: =#REF! -> #REF! | G758: =LEFT(C758,1)&SUBSTITUTE(SUBSTITUTE(SUBSTITUTE(SUBSTITUTE(SUBSTITUTE(SUBSTITUTE(SUBSTITUTE(RIGHT(C758,LEN(C758)-1),"a"," "),"e"," "),"i"," "),"o"," "),"u"," "),"y"," ")," ","") -> #REF! | H758: =LEFT(D758,1)&SUBSTITUTE(SUBSTITUTE(SUBSTITUTE(SUBSTITUTE(SUBSTITUTE(SUBSTITUTE(SUBSTITUTE(RIGHT(D758,LEN(D758)-1),"a"," "),"e"," "),"i"," "),"o"," "),"u"," "),"y"," ")," ","") -> #REF!
C759: =#REF! -> #REF! | D759: =#REF! -> #REF! | G759: =LEFT(C759,1)&SUBSTITUTE(SUBSTITUTE(SUBSTITUTE(SUBSTITUTE(SUBSTITUTE(SUBSTITUTE(SUBSTITUTE(RIGHT(C759,LEN(C759)-1),"a"," "),"e"," "),"i"," "),"o"," "),"u"," "),"y"," ")," ","") -> #REF! | H759: =LEFT(D759,1)&SUBSTITUTE(SUBSTITUTE(SUBSTITUTE(SUBSTITUTE(SUBSTITUTE(SUBSTITUTE(SUBSTITUTE(RIGHT(D759,LEN(D759)-1),"a"," "),"e"," "),"i"," "),"o"," "),"u"," "),"y"," ")," ","") -> #REF!
C760: =#REF! -> #REF! | D760: =#REF! -> #REF! | G760: =LEFT(C760,1)&SUBSTITUTE(SUBSTITUTE(SUBSTITUTE(SUBSTITUTE(SUBSTITUTE(SUBSTITUTE(SUBSTITUTE(RIGHT(C760,LEN(C760)-1),"a"," "),"e"," "),"i"," "),"o"," "),"u"," "),"y"," ")," ","") -> #REF! | H760: =LEFT(D760,1)&SUBSTITUTE(SUBSTITUTE(SUBSTITUTE(SUBSTITUTE(SUBSTITUTE(SUBSTITUTE(SUBSTITUTE(RIGHT(D760,LEN(D760)-1),"a"," "),"e"," "),"i"," "),"o"," "),"u"," "),"y"," ")," ","") -> #REF!
C761: =#REF! -> #REF! | D761: =#REF! -> #REF! | G761: =LEFT(C761,1)&SUBSTITUTE(SUBSTITUTE(SUBSTITUTE(SUBSTITUTE(SUBSTITUTE(SUBSTITUTE(SUBSTITUTE(RIGHT(C761,LEN(C761)-1),"a"," "),"e"," "),"i"," "),"o"," "),"u"," "),"y"," ")," ","") -> #REF! | H761: =LEFT(D761,1)&SUBSTITUTE(SUBSTITUTE(SUBSTITUTE(SUBSTITUTE(SUBSTITUTE(SUBSTITUTE(SUBSTITUTE(RIGHT(D761,LEN(D761)-1),"a"," "),"e"," "),"i"," "),"o"," "),"u"," "),"y"," ")," ","") -> #REF!
C762: =#REF! -> #REF! | D762: =#REF! -> #REF! | G762: =LEFT(C762,1)&SUBSTITUTE(SUBSTITUTE(SUBSTITUTE(SUBSTITUTE(SUBSTITUTE(SUBSTITUTE(SUBSTITUTE(RIGHT(C762,LEN(C762)-1),"a"," "),"e"," "),"i"," "),"o"," "),"u"," "),"y"," ")," ","") -> #REF! | H762: =LEFT(D762,1)&SUBSTITUTE(SUBSTITUTE(SUBSTITUTE(SUBSTITUTE(SUBSTITUTE(SUBSTITUTE(SUBSTITUTE(RIGHT(D762,LEN(D762)-1),"a"," "),"e"," "),"i"," "),"o"," "),"u"," "),"y"," ")," ","") -> #REF!
C763: =#REF! -> #REF! | D763: =#REF! -> #REF! | G763: =LEFT(C763,1)&SUBSTITUTE(SUBSTITUTE(SUBSTITUTE(SUBSTITUTE(SUBSTITUTE(SUBSTITUTE(SUBSTITUTE(RIGHT(C763,LEN(C763)-1),"a"," "),"e"," "),"i"," "),"o"," "),"u"," "),"y"," ")," ","") -> #REF! | H763: =LEFT(D763,1)&SUBSTITUTE(SUBSTITUTE(SUBSTITUTE(SUBSTITUTE(SUBSTITUTE(SUBSTITUTE(SUBSTITUTE(RIGHT(D763,LEN(D763)-1),"a"," "),"e"," "),"i"," "),"o"," "),"u"," "),"y"," ")," ","") -> #REF!
... C906: =#REF! -> #REF! | D906: =#REF! -> #REF! | G906: =LEFT(C906,1)&SUBSTITUTE(SUBSTITUTE(SUBSTITUTE(SUBSTITUTE(SUBSTITUTE(SUBSTITUTE(SUBSTITUTE(RIGHT(C906,LEN(C906)-1),"a"," "),"e"," "),"i"," "),"o"," "),"u"," "),"y"," ")," ","") -> #REF! | H906: =LEFT(D906,1)&SUBSTITUTE(SUBSTITUTE(SUBSTITUTE(SUBSTITUTE(SUBSTITUTE(SUBSTITUTE(SUBSTITUTE(RIGHT(D906,LEN(D906)-1),"a"," "),"e"," "),"i"," "),"o"," "),"u"," "),"y"," ")," ","") -> #REF!

Sheet ANNEXES

Sheet ISODateTime
A2: ISODateTime chez CAPE et ISOTime chez ATICA
A3: Definition: A particular point in the progression of time defined by a mandatory date and a mandatory time component, expressed in either UTC time format (YYYY-MM-DDThh:mm:ss.sssZ), local time with UTC offset format (YYYY-MM-DDThh:mm:ss.sss+/-hh:mm), or local time format (YYYY-MM- DDThh:mm:ss.sss). These representations are defined in "XML Schema Part 2: Datatypes Second Edition - W3C Recommendation 28 October 2004" which is aligned with ISO 8601. (Voir ci-dessous) Note on the time format: 1) beginning / end of calendar day 00:00:00 = the beginning of a calendar day 24:00:00 = the end of a calendar day 2) fractions of second in time format Decimal fractions of seconds may be included. In this case, the involved parties shall agree on the maximum number of digits that are allowed.
A5: XML Schema Part 2: Datatypes Second Edition - W3C Recommendation 28 October 2004"
A6: https://www.w3.org/TR/xmlschema-2/#dateTime
A7: The ·lexical space· of dateTime consists of finite-length sequences of characters of the form: '-'? yyyy '-' mm '-' dd 'T' hh ':' mm ':' ss ('.' s+)? (zzzzzz)?, where '-'? yyyy is a four-or-more digit optionally negative-signed numeral that represents the year; if more than four digits, leading zeros are prohibited, and '0000' is prohibited (see the Note above (§3.2.7); also note that a plus sign is not permitted); the remaining '-'s are separators between parts of the date portion; the first mm is a two-digit numeral that represents the month; dd is a two-digit numeral that represents the day; 'T' is a separator indicating that time-of-day follows; hh is a two-digit numeral that represents the hour; '24' is permitted if the minutes and seconds represented are zero, and the dateTime value so represented is the first instant of the following day (the hour property of a dateTime object in the ·value space· cannot have a value greater than 23); ':' is a separator between parts of the time-of-day portion; the second mm is a two-digit numeral that represents the minute; ss is a two-integer-digit numeral that represents the whole seconds; '.' s+ (if present) represents the fractional seconds; zzzzzz (if present) represents the timezone (as described below).

Sheet ISO 3166
A2: Source : https://www.iso.org/fr/iso-3166-country-codes.html
A3: ISO 3166 comprend trois parties: codes de pays, codes pour les subdivisions de pays et codes pour les noms de pays antérieurement utilisés (anciens codes pour désigner des pays, qui ne sont plus utilisés). Les codes de pays peuvent être représentés par un code à deux lettres (alpha-2) recommandé pour l’usage général, un code à trois lettres (alpha-3) associé plus étroitement au nom de pays, et un code à trois chiffres (numeric-3), utile lorsque les codes doivent être compris dans des pays n’utilisant pas l’alphabet latin. Les codes pour les subdivisions de pays sont représentés par le code de pays alpha-2, suivi de trois caractères maximum. Exemple: ID-RI est la province Riau d’Indonésie et NG-RI est la province Rivers du Nigéria. Les noms et codes de subdivisions proviennent en règle générale de sources d’information nationales officielles. Les codes pour les noms de pays antérieurement utilisés sont des codes à quatre lettres (alpha-4). La structure des codes alpha-4 dépend de la raison du retrait du nom de pays. Pour en savoir plus sur les différents types de codes, lisez le Glossaire ISO 3166.
